Workbook

Sheet crop
C1: Name of the indicator | D1: Yield wheat (grain) (UAA1) | E1: Yield wheat (straw) (UAA1) | F1: Yield barley (grain) (UAA1) | G1: Yield barley (straw) (UAA1) | H1: Yield sugar beet (UAA1) | I1: Yield potato (UAA1) | J1: Yield rapeseed (UAA1) | K1: Yield pea (UAA1) | L1: Yield faba bean (UAA1) | M1: Yield maize (UAA1) | N1: Yield alfalfa (UAA1) | O1: Yield sorghum (UAA1) | P1: Yield TG (UAA1) | Q1: Yield wheat (grain) (UAA2) | R1: Yield wheat (straw) (UAA2) | S1: Yield barley (grain) (UAA2) | T1: Yield barley (straw) (UAA2) | U1: Yield sugar beet (UAA2) | V1: Yield potato (UAA2) | W1: Yield rapeseed (UAA2) | X1: Yield pea (UAA2) | Y1: Yield faba bean (UAA2) | Z1: Yield maize (UAA2) | AA1: Yield alfalfa (UAA2) | AB1: Yield sorghum (UAA2) | AC1: Yield TG (UAA2) | AD1: Yield PG | AE1: Area wheat (UAA1) | AF1: Area barley (UAA1) | AG1: Area sugar beet (UAA1) | AH1: Area potato (UAA1) | AI1: Area rapeseed (UAA1) | AJ1: Area pea (UAA1) | AK1: Area faba bean (UAA1) | AL1: Area maize (UAA1) | AM1: Area alfalfa (UAA1) | AN1: Area sorghum (UAA1) | AO1: Area TG (UAA1) | AP1: Area wheat (UAA2) | AQ1: Area barley (UAA2) | AR1: Area sugar beet (UAA2) | AS1: Area potato (UAA2) | AT1: Area rapeseed (UAA2) | AU1: Area pea (UAA2) | AV1: Area faba bean (UAA2) | AW1: Area maize (UAA2) | AX1: Area alfalfa (UAA2) | AY1: Area sorghum (UAA2) | AZ1: Area TG (UAA2) | BA1: Area PG | BB1: N supply wheat (UAA1) | BC1: N supply barley (UAA1) | BD1: N supply sugar beet (UAA1) | BE1: N supply potato (UAA1) | BF1: N supply rapeseed (UAA1) | BG1: N supply pea (UAA1) | BH1: N supply faba bean (UAA1) | BI1: N supply maize (UAA1) | BJ1: N supply alfalfa (UAA1) | BK1: N supply sorghum (UAA1) | BL1: N supply TG (UAA1) | BM1: N supply wheat (UAA2) | BN1: N supply barley (UAA2) | BO1: N supply sugar beet (UAA2) | BP1: N supply potato (UAA2) | BQ1: N supply rapeseed (UAA2) | BR1: N supply pea (UAA2) | BS1: N supply faba bean (UAA2) | BT1: N supply maize (UAA2) | BU1: N supply alfalfa (UAA2) | BV1: N supply sorghum (UAA2) | BW1: N supply TG (UAA2) | BX1: N supply PG | BY1: TFI wheat (UAA1) | BZ1: TFI barley (UAA1) | CA1: TFI sugar beet (UAA1) | CB1: TFI potato (UAA1) | CC1: TFI rapeseed (UAA1) | CD1: TFI pea (UAA1) | CE1: TFI faba bean (UAA1) | CF1: TFI maize (UAA1) | CG1: TFI alfalfa (UAA1) | CH1: TFI sorghum (UAA1) | CI1: TFI TG (UAA1) | CJ1: TFI wheat (UAA2) | CK1: TFI barley (UAA2) | CL1: TFI sugar beet (UAA2) | CM1: TFI potato (UAA2) | CN1: TFI rapeseed (UAA2) | CO1: TFI pea (UAA2) | CP1: TFI faba bean (UAA2) | CQ1: TFI maize (UAA2) | CR1: TFI alfalfa (UAA2) | CS1: TFI sorghum (UAA2) | CT1: TFI TG (UAA2) | CU1: TFI PG
A2: AEP name | B2: AEP_ID | C2: IndicatorID | D2: =INDEX([1]indicators!$I$2:$I$1491,MATCH(D$1,[1]indicators!$C$2:$C$1491,0),1) -> indCr1.UAA1 | E2: =INDEX([1]indicators!$I$2:$I$1491,MATCH(E$1,[1]indicators!$C$2:$C$1491,0),1) -> indCr2.UAA1 | F2: =INDEX([1]indicators!$I$2:$I$1491,MATCH(F$1,[1]indicators!$C$2:$C$1491,0),1) -> indCr3.UAA1 | G2: =INDEX([1]indicators!$I$2:$I$1491,MATCH(G$1,[1]indicators!$C$2:$C$1491,0),1) -> indCr4.UAA1 | H2: =INDEX([1]indicators!$I$2:$I$1491,MATCH(H$1,[1]indicators!$C$2:$C$1491,0),1) -> indCr5.UAA1 | I2: =INDEX([1]indicators!$I$2:$I$1491,MATCH(I$1,[1]indicators!$C$2:$C$1491,0),1) -> indCr6.UAA1 | J2: =INDEX([1]indicators!$I$2:$I$1491,MATCH(J$1,[1]indicators!$C$2:$C$1491,0),1) -> indCr7.UAA1 | K2: =INDEX([1]indicators!$I$2:$I$1491,MATCH(K$1,[1]indicators!$C$2:$C$1491,0),1) -> indCr8.UAA1 | ... CU2: =INDEX([1]indicators!$I$2:$I$1491,MATCH(CU$1,[1]indicators!$C$2:$C$1491,0),1) -> indCr54
A3: =INDEX([1]AEP!$B$2:$B$113,MATCH($B3,[1]AEP!$C$2:$C$113,0),1) -> Conventional tillage (CT) | B3: C.1.1
A4: =INDEX([1]AEP!$B$2:$B$113,MATCH($B4,[1]AEP!$C$2:$C$113,0),1) -> Reduced tillage (RT) | B4: C.1.2
A5: =INDEX([1]AEP!$B$2:$B$113,MATCH($B5,[1]AEP!$C$2:$C$113,0),1) -> No tillage (NT) | B5: C.1.3 | D5: =1-0.08 -> 0.92 | F5: =1-0.08 -> 0.92 | H5: =1-0.08 -> 0.92 | I5: =1-0.08 -> 0.92 | J5: =1-0.08 -> 0.92 | K5: =1-0.08 -> 0.92 | L5: =1-0.08 -> 0.92 | M5: =1-0.08 -> 0.92 | N5: =1-0.08 -> 0.92 | O5: =1-0.08 -> 0.92 | Q5: 0.92 | S5: 0.92 | U5: 0.92 | V5: 0.92 | W5: 0.92 | X5: 0.92 | Y5: 0.92 | Z5: 0.92 | AA5: 0.92 | AB5: 0.92
A6: =INDEX([1]AEP!$B$2:$B$113,MATCH($B6,[1]AEP!$C$2:$C$113,0),1) -> Fall cover crop destructed before winter | B6: C.2.1 | BD6: 20 | BE6: 20 | BI6: 20 | BK6: 20 | BO6: 20 | BP6: 20 | BT6: 20 | BV6: 20
A7: =INDEX([1]AEP!$B$2:$B$113,MATCH($B7,[1]AEP!$C$2:$C$113,0),1) -> Fall cover crop destructed early spring | B7: C.2.2 | BD7: 20 | BE7: 20 | BI7: 20 | BK7: 20 | BO7: 20 | BP7: 20 | BT7: 20 | BV7: 20
A8: =INDEX([1]AEP!$B$2:$B$113,MATCH($B8,[1]AEP!$C$2:$C$113,0),1) -> Permanent soil cover | B8: C.2.3 | D8: =1-0.26 -> 0.74 | F8: =1-0.26 -> 0.74 | H8: =1-0.26 -> 0.74 | I8: =1-0.26 -> 0.74 | J8: =1-0.26 -> 0.74 | K8: =1-0.26 -> 0.74 | L8: =1-0.26 -> 0.74 | M8: =1-0.26 -> 0.74 | N8: =1-0.26 -> 0.74 | O8: =1-0.26 -> 0.74 | Q8: 0.74 | S8: 0.74 | U8: 0.74 | V8: 0.74 | W8: 0.74 | X8: 0.74 | Y8: 0.74 | Z8: 0.74 | AA8: 0.74 | AB8: 0.74 | BB8: =20/2 -> 10 | BC8: =20/2 -> 10 | BD8: =20/2 -> 10 | BE8: =20/2 -> 10 | BF8: =20/2 -> 10 | BI8: =20/2 -> 10 | BK8: =20/2 -> 10 | BM8: =20/2 -> 10 | BN8: =20/2 -> 10 | BO8: =20/2 -> 10 | BP8: =20/2 -> 10 | BQ8: =20/2 -> 10 | BT8: =20/2 -> 10 | BV8: =20/2 -> 10
A9: =INDEX([1]AEP!$B$2:$B$113,MATCH($B9,[1]AEP!$C$2:$C$113,0),1) -> Straw removal | B9: C.3.1
A10: =INDEX([1]AEP!$B$2:$B$113,MATCH($B10,[1]AEP!$C$2:$C$113,0),1) -> Straw left on soil | B10: C.3.2 | E10: 0 | G10: 0 | R10: 0 | T10: 0 | BB10: =-20/2 -> -10 | BC10: =-20/2 -> -10 | BD10: =-20/2 -> -10 | BE10: =-20/2 -> -10 | BF10: =-20/2 -> -10 | BI10: =-20/2 -> -10 | BK10: =-20/2 -> -10 | BM10: =-20/2 -> -10 | BN10: =-20/2 -> -10 | BO10: =-20/2 -> -10 | BP10: =-20/2 -> -10 | BQ10: =-20/2 -> -10 | BT10: =-20/2 -> -10 | BV10: =-20/2 -> -10
A11: =INDEX([1]AEP!$B$2:$B$113,MATCH($B11,[1]AEP!$C$2:$C$113,0),1) -> On-farm organic fertilizers + input of mineral fertilizer | B11: C.4.1
A12: =INDEX([1]AEP!$B$2:$B$113,MATCH($B12,[1]AEP!$C$2:$C$113,0),1) -> On-farm organic fertilizers only | B12: C.4.2
A13: =INDEX([1]AEP!$B$2:$B$113,MATCH($B13,[1]AEP!$C$2:$C$113,0),1) -> Systematic use of chemical fungicides | B13: C.5.1 | BY13: 3 | BZ13: 1 | CA13: 3 | CB13: 14 | CC13: 1 | CD13: 1 | CE13: 1 | CJ13: 3 | CK13: 1 | CL13: 3 | CM13: 14 | CN13: 1 | CO13: 1 | CP13: 1
A14: =INDEX([1]AEP!$B$2:$B$113,MATCH($B14,[1]AEP!$C$2:$C$113,0),1) -> Sound approach of chemical fungicides | B14: C.5.2 | BY14: 2 | CA14: 2 | CB14: 10 | CJ14: 2 | CL14: 2 | CM14: 10
A15: =INDEX([1]AEP!$B$2:$B$113,MATCH($B15,[1]AEP!$C$2:$C$113,0),1) -> Biocontrol products against diseases | B15: C.5.3 | D15: 0.85 | F15: 0.85 | H15: 0.92 | I15: 0.92 | J15: 0.95 | L15: 0.9 | M15: 0.95 | Q15: 0.85 | S15: 0.85 | U15: 0.92 | V15: 0.92 | W15: 0.95 | Y15: 0.9 | Z15: 0.95 | CA15: 1 | CB15: 14 | CL15: 1 | CM15: 14
A16: =INDEX([1]AEP!$B$2:$B$113,MATCH($B16,[1]AEP!$C$2:$C$113,0),1) -> No direct protection against diseases | B16: C.5.4 | D16: =1-0.15 -> 0.85 | F16: =1-0.15 -> 0.85 | H16: =1-0.15 -> 0.85 | I16: =1-0.15 -> 0.85 | J16: =1-0.15 -> 0.85 | K16: =1-0.15 -> 0.85 | L16: =1-0.15 -> 0.85 | M16: =1-0.15 -> 0.85 | N16: =1-0.15 -> 0.85 | O16: =1-0.15 -> 0.85 | Q16: 0.85 | S16: 0.85 | U16: 0.85 | V16: 0.85 | W16: 0.85 | X16: 0.85 | Y16: 0.85 | Z16: 0.85 | AA16: 0.85 | AB16: 0.85
A17: =INDEX([1]AEP!$B$2:$B$113,MATCH($B17,[1]AEP!$C$2:$C$113,0),1) -> Systematic and sole use of chemical herbicides | B17: C.6.1 | BY17: 2 | BZ17: 1 | CA17: 3 | CB17: 3 | CC17: 2 | CD17: 1 | CE17: 1 | CF17: 2 | CG17: 1 | CH17: 1 | CI17: 1 | CJ17: 2 | CK17: 1 | CL17: 3 | CM17: 3 | CN17: 2 | CO17: 1 | CP17: 1 | CQ17: 2 | CR17: 1 | CS17: 1 | CT17: 1
A18: =INDEX([1]AEP!$B$2:$B$113,MATCH($B18,[1]AEP!$C$2:$C$113,0),1) -> Sound approach of chemical herbicides + mechanical weed control | B18: C.6.2 | BY18: 1 | BZ18: 1 | CA18: 2 | CB18: 1 | CC18: 1 | CD18: 1 | CF18: 1 | CJ18: 1 | CK18: 1 | CL18: 2 | CM18: 1 | CN18: 1 | CO18: 1 | CQ18: 1
A19: =INDEX([1]AEP!$B$2:$B$113,MATCH($B19,[1]AEP!$C$2:$C$113,0),1) -> Sole use of mechanical weed control | B19: C.6.3
A20: =INDEX([1]AEP!$B$2:$B$113,MATCH($B20,[1]AEP!$C$2:$C$113,0),1) -> Systematic use of chemical insecticides / molluscicides / nematicides | B20: C.7.1 | BY20: 1 | CA20: 2 | CB20: 3 | CC20: 3 | CD20: 1 | CE20: 1 | CF20: 1 | CG20: 1 | CJ20: 1 | CL20: 2 | CM20: 3 | CN20: 3 | CO20: 1 | CP20: 1 | CQ20: 1 | CR20: 1
A21: =INDEX([1]AEP!$B$2:$B$113,MATCH($B21,[1]AEP!$C$2:$C$113,0),1) -> Sound approach of chemical insecticides / molluscicides / nematicides | B21: C.7.2 | I21: 0.92 | J21: 0.95 | K21: 0.95 | V21: 0.92 | W21: 0.95 | X21: 0.95 | CA21: 1 | CB21: 2 | CC21: 2 | CF21: 1 | CL21: 1 | CM21: 2 | CN21: 2 | CQ21: 1
A22: =INDEX([1]AEP!$B$2:$B$113,MATCH($B22,[1]AEP!$C$2:$C$113,0),1) -> Biocontrol products (incl. pyrethrin) and other natural control techniques against pests | B22: C.7.3 | H22: 0.9 | I22: 0.85 | J22: 0.9 | K22: 0.9 | U22: 0.9 | V22: 0.85 | W22: 0.9 | X22: 0.9 | CA22: 1 | CB22: 1 | CL22: 1 | CM22: 1
A23: =INDEX([1]AEP!$B$2:$B$113,MATCH($B23,[1]AEP!$C$2:$C$113,0),1) -> No direct protection against animal pests | B23: C.7.4 | H23: 0.8 | I23: 0.6 | J23: 0.8 | K23: 0.85 | L23: 0.9 | N23: 0.95 | U23: 0.8 | V23: 0.6 | W23: 0.8 | X23: 0.85 | Y23: 0.9 | AA23: 0.95
A24: =INDEX([1]AEP!$B$2:$B$113,MATCH($B24,[1]AEP!$C$2:$C$113,0),1) -> High yielding cultivars | B24: C.8.1
A25: =INDEX([1]AEP!$B$2:$B$113,MATCH($B25,[1]AEP!$C$2:$C$113,0),1) -> Resistant cultivars and/or mix of varieties | B25: C.8.2 | D25: =1-0.05 -> 0.95 | F25: =1-0.05 -> 0.95 | H25: =1-0.05 -> 0.95 | I25: =1-0.05 -> 0.95 | J25: =1-0.05 -> 0.95 | K25: =1-0.05 -> 0.95 | L25: =1-0.05 -> 0.95 | M25: =1-0.05 -> 0.95 | N25: =1-0.05 -> 0.95 | O25: =1-0.05 -> 0.95 | Q25: 0.95 | S25: 0.95 | U25: 0.95 | V25: 0.95 | W25: 0.95 | X25: 0.95 | Y25: 0.95 | Z25: 0.95 | AA25: 0.95 | AB25: 0.95
A26: =INDEX([1]AEP!$B$2:$B$113,MATCH($B26,[1]AEP!$C$2:$C$113,0),1) -> Temporary grassland composed of grass | B26: C.9.1
A27: =INDEX([1]AEP!$B$2:$B$113,MATCH($B27,[1]AEP!$C$2:$C$113,0),1) -> Temporary grassland composed of simple grass/legume mixtures | B27: C.9.2
A28: =INDEX([1]AEP!$B$2:$B$113,MATCH($B28,[1]AEP!$C$2:$C$113,0),1) -> Temporary grassland composed of complex grass/legume mixtures | B28: C.9.3
A29: =INDEX([1]AEP!$B$2:$B$113,MATCH($B29,[1]AEP!$C$2:$C$113,0),1) -> No permanent grassland | B29: C.10.1 | BA29: 0
A30: =INDEX([1]AEP!$B$2:$B$113,MATCH($B30,[1]AEP!$C$2:$C$113,0),1) -> Permanent grassland occupy a small percentage of the farm area | B30: C.10.2
A31: =INDEX([1]AEP!$B$2:$B$113,MATCH($B31,[1]AEP!$C$2:$C$113,0),1) -> Permanent grassland occupy a high percentage of the farm area | B31: C.10.3 | BA31: 2
A32: =INDEX([1]AEP!$B$2:$B$113,MATCH($B32,[1]AEP!$C$2:$C$113,0),1) -> Sole crops | B32: C.11.1 | AJ32: 0 | AU32: 0
A33: =INDEX([1]AEP!$B$2:$B$113,MATCH($B33,[1]AEP!$C$2:$C$113,0),1) -> Wheat/pea intercrops | B33: C.11.2 | D33: =1+0.12 -> 1.12 | E33: 0 | K33: 1.12 | Q33: 1.12 | R33: 0 | X33: 1.12 | AE33: 0.5 | AP33: 0.5 | BB33: 5 | BM33: 5
A34: =INDEX([1]AEP!$B$2:$B$113,MATCH($B34,[1]AEP!$C$2:$C$113,0),1) -> CS #1: maize - wheat | B34: C.12.1 | AE34: 0.5 | AF34: 0 | AG34: 0 | AH34: 0 | AI34: 0 | AK34: 0 | AL34: 0.5 | AM34: 0 | AN34: 0 | AO34: 0
A35: =INDEX([1]AEP!$B$2:$B$113,MATCH($B35,[1]AEP!$C$2:$C$113,0),1) -> CS #1: rapeseed - wheat - maize - wheat | B35: C.12.2 | AE35: 0.5 | AF35: 0 | AG35: 0 | AH35: 0 | AI35: 0.25 | AK35: 0 | AL35: 0.25 | AM35: 0 | AN35: 0 | AO35: 0 | BB35: =20/2 -> 10
A36: =INDEX([1]AEP!$B$2:$B$113,MATCH($B36,[1]AEP!$C$2:$C$113,0),1) -> CS #1: maize - wheat - maize - barley | B36: C.12.3 | AE36: 0.25 | AF36: 0.25 | AG36: 0 | AH36: 0 | AI36: 0 | AK36: 0 | AL36: 0.5 | AM36: 0 | AN36: 0 | AO36: 0
A37: =INDEX([1]AEP!$B$2:$B$113,MATCH($B37,[1]AEP!$C$2:$C$113,0),1) -> CS #1: alfalfa (3 years) - maize - wheat | B37: C.12.4 | AE37: 0.2 | AF37: 0 | AG37: 0 | AH37: 0 | AI37: 0 | AK37: 0 | AL37: 0.2 | AM37: 0.6 | AN37: 0 | AO37: 0 | BI37: 30
A38: =INDEX([1]AEP!$B$2:$B$113,MATCH($B38,[1]AEP!$C$2:$C$113,0),1) -> CS #1: faba bean - wheat - rapeseed - maize | B38: C.12.5 | AE38: 0.25 | AF38: 0 | AG38: 0 | AH38: 0 | AI38: 0.25 | AK38: 0.25 | AL38: 0.25 | AM38: 0 | AN38: 0 | AO38: 0 | BB38: 20 | BI38: 20
A39: =INDEX([1]AEP!$B$2:$B$113,MATCH($B39,[1]AEP!$C$2:$C$113,0),1) -> CS #1: grassland (4 years) - maize - maize | B39: C.12.6 | AE39: 0 | AF39: 0 | AG39: 0 | AH39: 0 | AI39: 0 | AK39: 0 | AL39: =2/6 -> 0.33333333 | AM39: 0 | AN39: 0 | AO39: =4/6 -> 0.66666667 | BI39: =(110+30)/2 -> 70
A40: =INDEX([1]AEP!$B$2:$B$113,MATCH($B40,[1]AEP!$C$2:$C$113,0),1) -> CS #1: grassland (3 years) - maize - wheat - barley | B40: C.12.7 | AE40: =1/6 -> 0.16666667 | AF40: =1/6 -> 0.16666667 | AG40: 0 | AH40: 0 | AI40: 0 | AK40: 0 | AL40: =1/6 -> 0.16666667 | AM40: 0 | AN40: 0 | AO40: =3/6 -> 0.5 | BI40: 70
A41: =INDEX([1]AEP!$B$2:$B$113,MATCH($B41,[1]AEP!$C$2:$C$113,0),1) -> CS #1: faba bean - wheat - maize - alfalfa (3 years) - barley - maize | B41: C.12.8 | AE41: =1/8 -> 0.125 | AF41: =1/8 -> 0.125 | AG41: 0 | AH41: 0 | AI41: 0 | AK41: =1/8 -> 0.125 | AL41: =2/8 -> 0.25 | AM41: =3/8 -> 0.375 | AN41: 0 | AO41: 0 | BB41: 20 | BC41: 30
A42: =INDEX([1]AEP!$B$2:$B$113,MATCH($B42,[1]AEP!$C$2:$C$113,0),1) -> CS #1: grassland (3 years) - maize - wheat - faba bean - rapeseed | B42: C.12.9 | AE42: =1/7 -> 0.14285714 | AF42: 0 | AG42: 0 | AH42: 0 | AI42: =1/7 -> 0.14285714 | AK42: =1/7 -> 0.14285714 | AL42: =1/7 -> 0.14285714 | AM42: 0 | AN42: 0 | AO42: =3/7 -> 0.42857143 | BF42: 20 | BI42: 70
A43: =INDEX([1]AEP!$B$2:$B$113,MATCH($B43,[1]AEP!$C$2:$C$113,0),1) -> CS #2: maize - wheat | B43: C.13.1 | AP43: 0.5 | AQ43: 0 | AR43: 0 | AS43: 0 | AT43: 0 | AV43: 0 | AW43: 0.5 | AX43: 0 | AY43: 0 | AZ43: 0
A44: =INDEX([1]AEP!$B$2:$B$113,MATCH($B44,[1]AEP!$C$2:$C$113,0),1) -> CS #2: rapeseed - wheat - maize - wheat | B44: C.13.2 | AP44: 0.5 | AQ44: 0 | AR44: 0 | AS44: 0 | AT44: 0.25 | AV44: 0 | AW44: 0.25 | AX44: 0 | AY44: 0 | AZ44: 0 | BM44: =20/2 -> 10
A45: =INDEX([1]AEP!$B$2:$B$113,MATCH($B45,[1]AEP!$C$2:$C$113,0),1) -> CS #2: maize - wheat - maize - barley | B45: C.13.3 | AP45: 0.25 | AQ45: 0.25 | AR45: 0 | AS45: 0 | AT45: 0 | AV45: 0 | AW45: 0.5 | AX45: 0 | AY45: 0 | AZ45: 0
A46: =INDEX([1]AEP!$B$2:$B$113,MATCH($B46,[1]AEP!$C$2:$C$113,0),1) -> CS #2: alfalfa (3 years) - maize - wheat | B46: C.13.4 | AP46: 0.2 | AQ46: 0 | AR46: 0 | AS46: 0 | AT46: 0 | AV46: 0 | AW46: 0.2 | AX46: 0.6 | AY46: 0 | AZ46: 0 | BT46: 30
A47: =INDEX([1]AEP!$B$2:$B$113,MATCH($B47,[1]AEP!$C$2:$C$113,0),1) -> CS #2: faba bean - wheat - rapeseed - maize | B47: C.13.5 | AP47: 0.25 | AQ47: 0 | AR47: 0 | AS47: 0 | AT47: 0.25 | AV47: 0.25 | AW47: 0.25 | AX47: 0 | AY47: 0 | AZ47: 0 | BM47: 20 | BT47: 20
A48: =INDEX([1]AEP!$B$2:$B$113,MATCH($B48,[1]AEP!$C$2:$C$113,0),1) -> CS #2: grassland (4 years) - maize - maize | B48: C.13.6 | AP48: 0 | AQ48: 0 | AR48: 0 | AS48: 0 | AT48: 0 | AV48: 0 | AW48: =2/6 -> 0.33333333 | AX48: 0 | AY48: 0 | AZ48: =4/6 -> 0.66666667 | BT48: =(110+30)/2 -> 70
A49: =INDEX([1]AEP!$B$2:$B$113,MATCH($B49,[1]AEP!$C$2:$C$113,0),1) -> CS #2: grassland (3 years) - maize - wheat - barley | B49: C.13.7 | AP49: =1/6 -> 0.16666667 | AQ49: =1/6 -> 0.16666667 | AR49: 0 | AS49: 0 | AT49: 0 | AV49: 0 | AW49: =1/6 -> 0.16666667 | AX49: 0 | AY49: 0 | AZ49: =3/6 -> 0.5 | BT49: 70
A50: =INDEX([1]AEP!$B$2:$B$113,MATCH($B50,[1]AEP!$C$2:$C$113,0),1) -> CS #2: faba bean - wheat - maize - alfalfa (3 years) - barley - maize | B50: C.13.8 | AP50: =1/8 -> 0.125 | AQ50: =1/8 -> 0.125 | AR50: 0 | AS50: 0 | AT50: 0 | AV50: =1/8 -> 0.125 | AW50: =2/8 -> 0.25 | AX50: =3/8 -> 0.375 | AY50: 0 | AZ50: 0 | BM50: 20 | BN50: 30
A51: =INDEX([1]AEP!$B$2:$B$113,MATCH($B51,[1]AEP!$C$2:$C$113,0),1) -> CS #2: grassland (3 years) - maize - wheat - faba bean - rapeseed | B51: C.13.9 | AP51: =1/7 -> 0.14285714 | AQ51: 0 | AR51: 0 | AS51: 0 | AT51: =1/7 -> 0.14285714 | AV51: =1/7 -> 0.14285714 | AW51: =1/7 -> 0.14285714 | AX51: 0 | AY51: 0 | AZ51: =3/7 -> 0.42857143 | BQ51: 20 | BT51: 70
A52: =INDEX([1]AEP!$B$2:$B$113,MATCH($B52,[1]AEP!$C$2:$C$113,0),1) -> No particular green infrastructure elements | B52: C.14.1
A53: =INDEX([1]AEP!$B$2:$B$113,MATCH($B53,[1]AEP!$C$2:$C$113,0),1) -> Sown field margins as green infrastructures: wildflowers strip | B53: C.14.2 | AE53: 0.95 | AF53: 0.95 | AG53: 0.95 | AH53: 0.95 | AI53: 0.95 | AK53: 0.95 | AL53: 0.95 | AM53: 0.95 | AN53: 0.95 | AO53: 0.95 | AP53: 0.95 | AQ53: 0.95 | AR53: 0.95 | AS53: 0.95 | AT53: 0.95 | AV53: 0.95 | AW53: 0.95 | AX53: 0.95 | AY53: 0.95 | AZ53: 0.95
A54: =INDEX([1]AEP!$B$2:$B$113,MATCH($B54,[1]AEP!$C$2:$C$113,0),1) -> Sown field margins as green infrastructures: beetle bank (for birds and polyphagous predator) | B54: C.14.3 | AE54: 0.95 | AF54: 0.95 | AG54: 0.95 | AH54: 0.95 | AI54: 0.95 | AK54: 0.95 | AL54: 0.95 | AM54: 0.95 | AN54: 0.95 | AO54: 0.95 | AP54: 0.95 | AQ54: 0.95 | AR54: 0.95 | AS54: 0.95 | AT54: 0.95 | AV54: 0.95 | AW54: 0.95 | AX54: 0.95 | AY54: 0.95 | AZ54: 0.95
A55: =INDEX([1]AEP!$B$2:$B$113,MATCH($B55,[1]AEP!$C$2:$C$113,0),1) -> Semi-natural field margins as green infrastructures: hedgerows | B55: C.14.4 | AE55: 0.95 | AF55: 0.95 | AG55: 0.95 | AH55: 0.95 | AI55: 0.95 | AK55: 0.95 | AL55: 0.95 | AM55: 0.95 | AN55: 0.95 | AO55: 0.95 | AP55: 0.95 | AQ55: 0.95 | AR55: 0.95 | AS55: 0.95 | AT55: 0.95 | AV55: 0.95 | AW55: 0.95 | AX55: 0.95 | AY55: 0.95 | AZ55: 0.95
A56: =INDEX([1]AEP!$B$2:$B$113,MATCH($B56,[1]AEP!$C$2:$C$113,0),1) -> Semi-natural field margins as green infrastructures: grass margins | B56: C.14.5 | AE56: 0.95 | AF56: 0.95 | AG56: 0.95 | AH56: 0.95 | AI56: 0.95 | AK56: 0.95 | AL56: 0.95 | AM56: 0.95 | AN56: 0.95 | AO56: 0.95 | AP56: 0.95 | AQ56: 0.95 | AR56: 0.95 | AS56: 0.95 | AT56: 0.95 | AV56: 0.95 | AW56: 0.95 | AX56: 0.95 | AY56: 0.95 | AZ56: 0.95
A57: =INDEX([1]AEP!$B$2:$B$113,MATCH($B57,[1]AEP!$C$2:$C$113,0),1) -> No agroforestry | B57: C.15.1
A58: =INDEX([1]AEP!$B$2:$B$113,MATCH($B58,[1]AEP!$C$2:$C$113,0),1) -> In-field agroforestry | B58: C.15.2 | AE58: 0.84 | AF58: 0.84 | AG58: 0.84 | AH58: 0.84 | AI58: 0.84 | AK58: 0.84 | AL58: 0.84 | AM58: 0.84 | AN58: 0.84 | AO58: 0.84 | AP58: 0.84 | AQ58: 0.84 | AR58: 0.84 | AS58: 0.84 | AT58: 0.84 | AV58: 0.84 | AW58: 0.84 | AX58: 0.84 | AY58: 0.84 | AZ58: 0.84
A59: =INDEX([1]AEP!$B$2:$B$113,MATCH($B59,[1]AEP!$C$2:$C$113,0),1) -> Balanced strategy between farmer income and investment | B59: E.1.1
A60: =INDEX([1]AEP!$B$2:$B$113,MATCH($B60,[1]AEP!$C$2:$C$113,0),1) -> Investment-oriented strategy | B60: E.1.2
A61: =INDEX([1]AEP!$B$2:$B$113,MATCH($B61,[1]AEP!$C$2:$C$113,0),1) -> Income-oriented strategy | B61: E.1.3
A62: =INDEX([1]AEP!$B$2:$B$113,MATCH($B62,[1]AEP!$C$2:$C$113,0),1) -> Conventional farming | B62: G.1.1
A63: =INDEX([1]AEP!$B$2:$B$113,MATCH($B63,[1]AEP!$C$2:$C$113,0),1) -> Organic farming | B63: G.1.2
A64: =INDEX([1]AEP!$B$2:$B$113,MATCH($B64,[1]AEP!$C$2:$C$113,0),1) -> Cattle breed is Holstein | B64: A.1.1
A65: =INDEX([1]AEP!$B$2:$B$113,MATCH($B65,[1]AEP!$C$2:$C$113,0),1) -> Cattle breed is Siemmental | B65: A.1.2
A66: =INDEX([1]AEP!$B$2:$B$113,MATCH($B66,[1]AEP!$C$2:$C$113,0),1) -> Cattle breed is Montbéliarde | B66: A.1.3
A67: =INDEX([1]AEP!$B$2:$B$113,MATCH($B67,[1]AEP!$C$2:$C$113,0),1) -> Initial herd size | B67: A.2.1
A68: =INDEX([1]AEP!$B$2:$B$113,MATCH($B68,[1]AEP!$C$2:$C$113,0),1) -> 15% increase of initial herd size (no building modification) | B68: A.2.2
A69: =INDEX([1]AEP!$B$2:$B$113,MATCH($B69,[1]AEP!$C$2:$C$113,0),1) -> 15% increase of initial herd size (building modification) | B69: A.2.3
A70: =INDEX([1]AEP!$B$2:$B$113,MATCH($B70,[1]AEP!$C$2:$C$113,0),1) -> 30% increase of initial herd size (building modification) | B70: A.2.4
... A75: =INDEX([1]AEP!$B$2:$B$113,MATCH($B75,[1]AEP!$C$2:$C$113,0),1) -> Male calves sold at 8 days | B75: A.3.3
A76: =INDEX([1]AEP!$B$2:$B$113,MATCH($B76,[1]AEP!$C$2:$C$113,0),1) -> Cows are tied on straw bedding | B76: A.4.1 | BB76: =50/2 -> 25 | BC76: =30/2 -> 15 | BD76: =70/0.7/2 -> 50 | BE76: =70/2 -> 35 | BF76: =40/2 -> 20 | BI76: =70/2 -> 35 | BK76: =70/2 -> 35 | BL76: =83/2 -> 41.5 | BM76: =50/2 -> 25 | BN76: =30/2 -> 15 | BO76: =70/0.7/2 -> 50 | BP76: =70/2 -> 35 | BQ76: =40/2 -> 20 | BT76: =70/2 -> 35 | BV76: =70/2 -> 35 | BW76: =83/2 -> 41.5 | BX76: =50/2 -> 25
A77: =INDEX([1]AEP!$B$2:$B$113,MATCH($B77,[1]AEP!$C$2:$C$113,0),1) -> Housing of cows is cubicles with straw (shallow bedding) | B77: A.4.2 | BB77: =50/2 -> 25 | BC77: =30/2 -> 15 | BD77: =70/0.7/2 -> 50 | BE77: =70/2 -> 35 | BF77: =40/2 -> 20 | BI77: =70/2 -> 35 | BK77: =70/2 -> 35 | BL77: =83/2 -> 41.5 | BM77: =50/2 -> 25 | BN77: =30/2 -> 15 | BO77: =70/0.7/2 -> 50 | BP77: =70/2 -> 35 | BQ77: =40/2 -> 20 | BT77: =70/2 -> 35 | BV77: =70/2 -> 35 | BW77: =83/2 -> 41.5 | BX77: =50/2 -> 25
A78: =INDEX([1]AEP!$B$2:$B$113,MATCH($B78,[1]AEP!$C$2:$C$113,0),1) -> Housing of cows is cubicles with slatted floor | B78: A.4.3 | BB78: =25/2 -> 12.5 | BC78: =15/2 -> 7.5 | BD78: =35/0.7/2 -> 25 | BE78: =35/2 -> 17.5 | BF78: =20/2 -> 10 | BI78: =35/2 -> 17.5 | BK78: =35/2 -> 17.5 | BL78: =60/2 -> 30 | BM78: =25/2 -> 12.5 | BN78: =15/2 -> 7.5 | BO78: =35/0.7/2 -> 25 | BP78: =35/2 -> 17.5 | BQ78: =20/2 -> 10 | BT78: =35/2 -> 17.5 | BV78: =35/2 -> 17.5 | BW78: =60/2 -> 30 | BX78: =36/2 -> 18
A79: =INDEX([1]AEP!$B$2:$B$113,MATCH($B79,[1]AEP!$C$2:$C$113,0),1) -> Housing of cows is free-stall (deep bedding) | B79: A.4.4 | BB79: =50/2 -> 25 | BC79: =30/2 -> 15 | BD79: =70/0.7/2 -> 50 | BE79: =70/2 -> 35 | BF79: =40/2 -> 20 | BI79: =70/2 -> 35 | BK79: =70/2 -> 35 | BL79: =83/2 -> 41.5 | BM79: =50/2 -> 25 | BN79: =30/2 -> 15 | BO79: =70/0.7/2 -> 50 | BP79: =70/2 -> 35 | BQ79: =40/2 -> 20 | BT79: =70/2 -> 35 | BV79: =70/2 -> 35 | BW79: =83/2 -> 41.5 | BX79: =50/2 -> 25
A80: =INDEX([1]AEP!$B$2:$B$113,MATCH($B80,[1]AEP!$C$2:$C$113,0),1) -> Housing of cows is free-stall slatted floor | B80: A.4.5 | BB80: =25/2 -> 12.5 | BC80: =15/2 -> 7.5 | BD80: =35/0.7/2 -> 25 | BE80: =35/2 -> 17.5 | BF80: =20/2 -> 10 | BI80: =35/2 -> 17.5 | BK80: =35/2 -> 17.5 | BL80: =60/2 -> 30 | BM80: =25/2 -> 12.5 | BN80: =15/2 -> 7.5 | BO80: =35/0.7/2 -> 25 | BP80: =35/2 -> 17.5 | BQ80: =20/2 -> 10 | BT80: =35/2 -> 17.5 | BV80: =35/2 -> 17.5 | BW80: =60/2 -> 30 | BX80: =36/2 -> 18
A81: =INDEX([1]AEP!$B$2:$B$113,MATCH($B81,[1]AEP!$C$2:$C$113,0),1) -> Housing of heifer, bulls and steers is slatted floor | B81: A.5.1 | BB81: =25/2 -> 12.5 | BC81: =15/2 -> 7.5 | BD81: =35/0.7/2 -> 25 | BE81: =35/2 -> 17.5 | BF81: =20/2 -> 10 | BI81: =35/2 -> 17.5 | BK81: =35/2 -> 17.5 | BL81: =60/2 -> 30 | BM81: =25/2 -> 12.5 | BN81: =15/2 -> 7.5 | BO81: =35/0.7/2 -> 25 | BP81: =35/2 -> 17.5 | BQ81: =20/2 -> 10 | BT81: =35/2 -> 17.5 | BV81: =35/2 -> 17.5 | BW81: =60/2 -> 30 | BX81: =36/2 -> 18
A82: =INDEX([1]AEP!$B$2:$B$113,MATCH($B82,[1]AEP!$C$2:$C$113,0),1) -> Housing of heifer, bulls and steers is shallow bedding | B82: A.5.2 | BB82: =50/2 -> 25 | BC82: =30/2 -> 15 | BD82: =70/0.7/2 -> 50 | BE82: =70/2 -> 35 | BF82: =40/2 -> 20 | BI82: =70/2 -> 35 | BK82: =70/2 -> 35 | BL82: =83/2 -> 41.5 | BM82: =50/2 -> 25 | BN82: =30/2 -> 15 | BO82: =70/0.7/2 -> 50 | BP82: =70/2 -> 35 | BQ82: =40/2 -> 20 | BT82: =70/2 -> 35 | BV82: =70/2 -> 35 | BW82: =83/2 -> 41.5 | BX82: =50/2 -> 25
A83: =INDEX([1]AEP!$B$2:$B$113,MATCH($B83,[1]AEP!$C$2:$C$113,0),1) -> Housing of heifer, bulls and steers is deep bedding | B83: A.5.3 | BB83: =50/2 -> 25 | BC83: =30/2 -> 15 | BD83: =70/0.7/2 -> 50 | BE83: =70/2 -> 35 | BF83: =40/2 -> 20 | BI83: =70/2 -> 35 | BK83: =70/2 -> 35 | BL83: =83/2 -> 41.5 | BM83: =50/2 -> 25 | BN83: =30/2 -> 15 | BO83: =70/0.7/2 -> 50 | BP83: =70/2 -> 35 | BQ83: =40/2 -> 20 | BT83: =70/2 -> 35 | BV83: =70/2 -> 35 | BW83: =83/2 -> 41.5 | BX83: =50/2 -> 25
A84: =INDEX([1]AEP!$B$2:$B$113,MATCH($B84,[1]AEP!$C$2:$C$113,0),1) -> Cow feeding system: all year indoor, maize silage & soybean meal supplement | B84: A.6.1 | BL84: =-30/2 -> -15 | BW84: =-30/2 -> -15 | BX84: -15
A85: =INDEX([1]AEP!$B$2:$B$113,MATCH($B85,[1]AEP!$C$2:$C$113,0),1) -> Cow feeding system: all year indoor, sorghum silage & soybean meal supplement | B85: A.6.2 | BL85: =-30/2 -> -15 | BW85: =-30/2 -> -15 | BX85: -15
A86: =INDEX([1]AEP!$B$2:$B$113,MATCH($B86,[1]AEP!$C$2:$C$113,0),1) -> Cow feeding system: all year indoor, sorghum & alfalfa silage | B86: A.6.3 | BL86: =-30/2 -> -15 | BW86: =-30/2 -> -15 | BX86: -15
A87: =INDEX([1]AEP!$B$2:$B$113,MATCH($B87,[1]AEP!$C$2:$C$113,0),1) -> Cow feeding system: all year indoor, maize silage, alfalfa silage & soybean meal supplement | B87: A.6.4 | BL87: =-30/2 -> -15 | BW87: =-30/2 -> -15 | BX87: -15
A88: =INDEX([1]AEP!$B$2:$B$113,MATCH($B88,[1]AEP!$C$2:$C$113,0),1) -> Cow feeding system: 4 months grazing & soybean meal supplement | B88: A.6.5
A89: =INDEX([1]AEP!$B$2:$B$113,MATCH($B89,[1]AEP!$C$2:$C$113,0),1) -> Cow feeding system: 4 months grazing & rapeseed meal supplement | B89: A.6.6
A90: =INDEX([1]AEP!$B$2:$B$113,MATCH($B90,[1]AEP!$C$2:$C$113,0),1) -> Cow feeding system: 5 months grazing & rapeseed meal supplement | B90: A.6.7
A91: =INDEX([1]AEP!$B$2:$B$113,MATCH($B91,[1]AEP!$C$2:$C$113,0),1) -> Cow feeding system: 7 months grazing & rapeseed meal supplement | B91: A.6.8
A92: =INDEX([1]AEP!$B$2:$B$113,MATCH($B92,[1]AEP!$C$2:$C$113,0),1) -> Cow feeding system: 8 months grazing & faba bean supplement | B92: A.6.9
A93: =INDEX([1]AEP!$B$2:$B$113,MATCH($B93,[1]AEP!$C$2:$C$113,0),1) -> Cow feeding system: all year indoor, hay & rapeseed meal supplement | B93: A.6.10 | BL93: =-30/2 -> -15 | BW93: =-30/2 -> -15 | BX93: -15
A94: =INDEX([1]AEP!$B$2:$B$113,MATCH($B94,[1]AEP!$C$2:$C$113,0),1) -> Cow feeding system: 9 months grazing, without protein feed supplement | B94: A.6.11
A95: =INDEX([1]AEP!$B$2:$B$113,MATCH($B95,[1]AEP!$C$2:$C$113,0),1) -> No concentrate supply for lactating dairy cows | B95: A.7.1
A96: =INDEX([1]AEP!$B$2:$B$113,MATCH($B96,[1]AEP!$C$2:$C$113,0),1) -> +1000 kg / cow / year with soybean meal and cereals | B96: A.7.2
A97: =INDEX([1]AEP!$B$2:$B$113,MATCH($B97,[1]AEP!$C$2:$C$113,0),1) -> +500 kg / cow / year with soybean meal and cereals | B97: A.7.3
A98: =INDEX([1]AEP!$B$2:$B$113,MATCH($B98,[1]AEP!$C$2:$C$113,0),1) -> +500 kg / cow / year with faba bean and cereals | B98: A.7.4
A99: =INDEX([1]AEP!$B$2:$B$113,MATCH($B99,[1]AEP!$C$2:$C$113,0),1) -> Heifer feeding system: zero grazing / maize silage + soybean meal | Age at first calving: 24 months | B99: A.8.1 | BL99: =-30/2 -> -15 | BW99: =-30/2 -> -15 | BX99: -15
A100: =INDEX([1]AEP!$B$2:$B$113,MATCH($B100,[1]AEP!$C$2:$C$113,0),1) -> Heifer feeding system: 4 months grazing / 8 months maize silage + hay + soybean meal | Age at first calving: 24 months | B100: A.8.2
A101: =INDEX([1]AEP!$B$2:$B$113,MATCH($B101,[1]AEP!$C$2:$C$113,0),1) -> Heifer feeding system: 6 months grazing / 6 months maize silage + grass silage (or hay) + soybean meal | Age at first calving: 24 months | B101: A.8.3
A102: =INDEX([1]AEP!$B$2:$B$113,MATCH($B102,[1]AEP!$C$2:$C$113,0),1) -> Heifer feeding system: 6 months grazing / 6 months grass silage (or hay) + cereals + soybean meal | Age at first calving: 24 months | B102: A.8.4
A103: =INDEX([1]AEP!$B$2:$B$113,MATCH($B103,[1]AEP!$C$2:$C$113,0),1) -> Heifer feeding system: zero grazing / maize silage + soybean meal | Age at first calving: 29 months | B103: A.8.5 | BL103: =-30/2 -> -15 | BW103: =-30/2 -> -15 | BX103: -15
A104: =INDEX([1]AEP!$B$2:$B$113,MATCH($B104,[1]AEP!$C$2:$C$113,0),1) -> Heifer feeding system: 4 months grazing / 8 months maize silage + hay + soybean meal | Age at first calving: 29 months | B104: A.8.6
...

Sheet environment
C1: Name of the indicator | D1: Natural enemies (UAA1) | E1: Natural enemies (UAA2) | F1: Natural enemies (PG) | G1: Microbial biomass (UAA1) | H1: Microbial biomass (UAA2) | I1: Microbial biomass (PG) | J1: Soil meso-fauna - nematodes (UAA1) | K1: Soil meso-fauna - nematodes (UAA2) | L1: Soil meso-fauna - nematodes (PG) | M1: Earthworm abundance (UAA1) | N1: Earthworm abundance (UAA2) | O1: Earthworm abundance (PG) | P1: Pollinators (UAA1) | Q1: Pollinators (UAA2) | R1: Pollinators (PG) | S1: Soil Organic Carbon (SOC) (UAA1) | T1: Soil Organic Carbon (SOC) (UAA2) | U1: Soil Organic Carbon (SOC) (PG) | V1: N content (UAA1) | W1: N content (UAA2) | X1: N content (PG) | Y1: P content (UAA1) | Z1: P content (UAA2) | AA1: P content (PG) | AB1: Soil water holding capacity (UAA1) | AC1: Soil water holding capacity (UAA2) | AD1: Soil water holding capacity (PG) | AE1: Soil water infiltration (UAA1) | AF1: Soil water infiltration (UAA2) | AG1: Soil water infiltration (PG) | AH1: Resistance of soil to erosion (UAA1) | AI1: Resistance of soil to erosion (UAA2) | AJ1: Resistance of soil to erosion (PG) | AK1: Water quality pesticides (UAA1) | AL1: Water quality pesticides (UAA2) | AM1: Water quality pesticides (PG) | AN1: Water quality nitrates (UAA1) | AO1: Water quality nitrates (UAA2) | AP1: Water quality nitrates (PG)
A2: AEP name | B2: AEP_ID | C2: IndicatorID | D2: =INDEX([1]indicators!$I$2:$I$1491,MATCH(D$1,[1]indicators!$C$2:$C$1491,0),1) -> indCr55.UAA1 | E2: =INDEX([1]indicators!$I$2:$I$1491,MATCH(E$1,[1]indicators!$C$2:$C$1491,0),1) -> indCr55.UAA2 | F2: =INDEX([1]indicators!$I$2:$I$1491,MATCH(F$1,[1]indicators!$C$2:$C$1491,0),1) -> indCr56 | G2: =INDEX([1]indicators!$I$2:$I$1491,MATCH(G$1,[1]indicators!$C$2:$C$1491,0),1) -> indCr57.UAA1 | H2: =INDEX([1]indicators!$I$2:$I$1491,MATCH(H$1,[1]indicators!$C$2:$C$1491,0),1) -> indCr57.UAA2 | I2: =INDEX([1]indicators!$I$2:$I$1491,MATCH(I$1,[1]indicators!$C$2:$C$1491,0),1) -> indCr58 | J2: =INDEX([1]indicators!$I$2:$I$1491,MATCH(J$1,[1]indicators!$C$2:$C$1491,0),1) -> indCr59.UAA1 | K2: =INDEX([1]indicators!$I$2:$I$1491,MATCH(K$1,[1]indicators!$C$2:$C$1491,0),1) -> indCr59.UAA2 | ... AP2: =INDEX([1]indicators!$I$2:$I$1491,MATCH(AP$1,[1]indicators!$C$2:$C$1491,0),1) -> indCr236
A3: =crop!A3 -> Conventional tillage (CT) | B3: =crop!B3 -> C.1.1 | D3: 0.9 | E3: 0.9 | G3: -1 | H3: -1 | J3: 0.8 | K3: 0.8 | M3: -1 | N3: -1 | V3: -0.5 | W3: -0.5 | Y3: -1 | Z3: -1
A4: =crop!A4 -> Reduced tillage (RT) | B4: =crop!B4 -> C.1.2 | D4: 1.01 | E4: 1.01 | G4: 1 | H4: 1 | J4: 1.1 | K4: 1.1 | M4: 1 | N4: 1 | P4: 1.01 | Q4: 1.01 | V4: -0.5 | W4: -0.5 | Y4: 1 | Z4: 1 | AH4: 0.5 | AI4: 0.5
A5: =crop!A5 -> No tillage (NT) | B5: =crop!B5 -> C.1.3 | D5: 1.05 | E5: 1.05 | G5: 2 | H5: 2 | J5: 1.2 | K5: 1.2 | M5: 2 | N5: 2 | P5: 1.03 | Q5: 1.03 | V5: 1 | W5: 1 | Y5: 1 | Z5: 1 | AE5: 0.5 | AF5: 0.5 | AH5: 1 | AI5: 1
A6: =crop!A6 -> Fall cover crop destructed before winter | B6: =crop!B6 -> C.2.1 | J6: 0.9 | K6: 0.9 | V6: 1 | W6: 1
A7: =crop!A7 -> Fall cover crop destructed early spring | B7: =crop!B7 -> C.2.2 | D7: 1.05 | E7: 1.05 | G7: 1 | H7: 1 | J7: 1.05 | K7: 1.05 | M7: 1 | N7: 1 | V7: 1 | W7: 1 | AH7: 0.5 | AI7: 0.5 | AN7: 0.5 | AO7: 0.5
A8: =crop!A8 -> Permanent soil cover | B8: =crop!B8 -> C.2.3 | D8: 1.1 | E8: 1.1 | G8: 2 | H8: 2 | J8: 1.1 | K8: 1.1 | M8: 2 | N8: 2 | S8: 1 | T8: 1 | V8: 2 | W8: 2 | AH8: 2 | AI8: 2 | AN8: 1 | AO8: 1
A9: =crop!A9 -> Straw removal | B9: =crop!B9 -> C.3.1 | G9: -1 | H9: -1 | M9: -1 | N9: -1 | S9: -1 | T9: -1 | V9: -0.5 | W9: -0.5 | Y9: -2 | Z9: -2 | AE9: -1 | AF9: -1
A10: =crop!A10 -> Straw left on soil | B10: =crop!B10 -> C.3.2 | D10: 1.02 | E10: 1.02 | G10: 2 | H10: 2 | J10: 1.02 | K10: 1.02 | M10: 1 | N10: 1 | S10: 0.5 | T10: 0.5 | V10: 1 | W10: 1 | Y10: -1 | Z10: -1 | AE10: 2 | AF10: 2 | AH10: 1 | AI10: 1
A11: =crop!A11 -> On-farm organic fertilizers + input of mineral fertilizer | B11: =crop!B11 -> C.4.1 | S11: 2 | T11: 2 | Y11: 0.5 | Z11: 0.5
A12: =crop!A12 -> On-farm organic fertilizers only | B12: =crop!B12 -> C.4.2 | S12: 1 | T12: 1
A13: =crop!A13 -> Systematic use of chemical fungicides | B13: =crop!B13 -> C.5.1 | G13: -1 | H13: -1 | M13: -1 | N13: -1 | P13: 0.9 | Q13: 0.9 | AK13: -1 | AL13: -1
A14: =crop!A14 -> Sound approach of chemical fungicides | B14: =crop!B14 -> C.5.2 | D14: 1.01 | E14: 1.01 | J14: 1.01 | K14: 1.01 | AK14: -0.5 | AL14: -0.5
A15: =crop!A15 -> Biocontrol products against diseases | B15: =crop!B15 -> C.5.3 | D15: 1.02 | E15: 1.02 | J15: 1.02 | K15: 1.02 | P15: 1.02 | Q15: 1.02
A16: =crop!A16 -> No direct protection against diseases | B16: =crop!B16 -> C.5.4 | D16: 1.03 | E16: 1.03 | G16: 1 | H16: 1 | J16: 1.03 | K16: 1.03 | M16: 1 | N16: 1 | P16: 1.03 | Q16: 1.03 | AK16: =1 -> 1 | AL16: =1 -> 1
A17: =crop!A17 -> Systematic and sole use of chemical herbicides | B17: =crop!B17 -> C.6.1 | D17: 0.9 | E17: 0.9 | J17: 0.9 | K17: 0.9 | P17: 0.9 | Q17: 0.9 | AK17: -1 | AL17: -1
A18: =crop!A18 -> Sound approach of chemical herbicides + mechanical weed control | B18: =crop!B18 -> C.6.2 | D18: 1.01 | E18: 1.01 | G18: -0.5 | H18: -0.5 | J18: 1.01 | K18: 1.01 | P18: 1.01 | Q18: 1.01 | AK18: -0.5 | AL18: -0.5
A19: =crop!A19 -> Sole use of mechanical weed control | B19: =crop!B19 -> C.6.3 | D19: 1.02 | E19: 1.02 | G19: -1 | H19: -1 | J19: 1.02 | K19: 1.02 | M19: -1 | N19: -1 | P19: 1.02 | Q19: 1.02 | V19: -0.5 | W19: -0.5 | AE19: -0.5 | AF19: -0.5 | AH19: -0.5 | AI19: -0.5 | AK19: 1 | AL19: 1
A20: =crop!A20 -> Systematic use of chemical insecticides / molluscicides / nematicides | B20: =crop!B20 -> C.7.1 | D20: 0.8 | E20: 0.8 | J20: 0.8 | K20: 0.8 | M20: -2 | N20: -2 | P20: 0.8 | Q20: 0.8 | AK20: -1 | AL20: -1
A21: =crop!A21 -> Sound approach of chemical insecticides / molluscicides / nematicides | B21: =crop!B21 -> C.7.2 | M21: -0.5 | N21: -0.5 | AK21: -0.5 | AL21: -0.5
A22: =crop!A22 -> Biocontrol products (incl. pyrethrin) and other natural control techniques against pests | B22: =crop!B22 -> C.7.3 | D22: 1.05 | E22: 1.05 | J22: 1.05 | K22: 1.05 | P22: 1.05 | Q22: 1.05
A23: =crop!A23 -> No direct protection against animal pests | B23: =crop!B23 -> C.7.4 | D23: 1.2 | E23: 1.2 | G23: 0.5 | H23: 0.5 | J23: 1.2 | K23: 1.2 | M23: 2 | N23: 2 | P23: 1.2 | Q23: 1.2 | AK23: =1 -> 1 | AL23: =1 -> 1
A24: =crop!A24 -> High yielding cultivars | B24: =crop!B24 -> C.8.1 | Y24: -2 | Z24: -2
A25: =crop!A25 -> Resistant cultivars and/or mix of varieties | B25: =crop!B25 -> C.8.2 | Y25: -0.5 | Z25: -0.5
A26: =crop!A26 -> Temporary grassland composed of grass | B26: =crop!B26 -> C.9.1 | G26: 1 | H26: 1 | M26: 1 | N26: 1 | V26: 1 | W26: 1 | Y26: -1 | Z26: -1 | AB26: 1 | AC26: 1 | AE26: 0.5 | AF26: 0.5
A27: =crop!A27 -> Temporary grassland composed of simple grass/legume mixtures | B27: =crop!B27 -> C.9.2 | D27: 1.02 | E27: 1.02 | G27: 2 | H27: 2 | J27: 1.02 | K27: 1.02 | M27: 2 | N27: 2 | P27: 1.02 | Q27: 1.02 | V27: 1 | W27: 1 | Y27: 1 | Z27: 1 | AB27: 1 | AC27: 1 | AE27: 0.5 | AF27: 0.5
A28: =crop!A28 -> Temporary grassland composed of complex grass/legume mixtures | B28: =crop!B28 -> C.9.3 | D28: 1.05 | E28: 1.05 | G28: 2 | H28: 2 | J28: 1.05 | K28: 1.05 | M28: 2 | N28: 2 | P28: 1.05 | Q28: 1.05 | V28: 1 | W28: 1 | Y28: 2 | Z28: 2 | AB28: 1 | AC28: 1 | AE28: 0.5 | AF28: 0.5
A29: =crop!A29 -> No permanent grassland | B29: =crop!B29 -> C.10.1 | F29: 0.8 | I29: -1 | L29: 0.8 | O29: -1 | R29: 0.8 | X29: -1 | AD29: -1 | AG29: -1
A30: =crop!A30 -> Permanent grassland occupy a small percentage of the farm area | B30: =crop!B30 -> C.10.2 | I30: 1 | O30: 1 | X30: 1 | AA30: 1 | AD30: 1 | AG30: 1
A31: =crop!A31 -> Permanent grassland occupy a high percentage of the farm area | B31: =crop!B31 -> C.10.3 | F31: 1.05 | I31: 2 | L31: 1.05 | O31: 2 | X31: 2 | AA31: 2 | AD31: 1 | AG31: 1
A32: =crop!A32 -> Sole crops | B32: =crop!B32 -> C.11.1 | G32: -1 | H32: -1 | M32: -1 | N32: -1
A33: =crop!A33 -> Wheat/pea intercrops | B33: =crop!B33 -> C.11.2 | D33: 1.1 | E33: 1.1 | G33: 1 | H33: 1 | J33: 1.05 | K33: 1.05 | M33: 1 | N33: 1 | P33: 1.1 | Q33: 1.1 | S33: 1 | T33: 1 | V33: 0.5 | W33: 0.5 | Y33: 0.5 | Z33: 0.5 | AN33: 0.25 | AO33: 0.25
A34: =crop!A34 -> CS #1: maize - wheat | B34: =crop!B34 -> C.12.1 | G34: -1 | Y34: -2
A35: =crop!A35 -> CS #1: rapeseed - wheat - maize - wheat | B35: =crop!B35 -> C.12.2 | D35: 1.02 | J35: 1.02 | P35: 1.02 | Y35: -2 | AE35: 0.5
A36: =crop!A36 -> CS #1: maize - wheat - maize - barley | B36: =crop!B36 -> C.12.3 | D36: 1.02 | J36: 1.02 | P36: 1.02 | Y36: -2 | AE36: 0.5
A37: =crop!A37 -> CS #1: alfalfa (3 years) - maize - wheat | B37: =crop!B37 -> C.12.4 | D37: 1.04 | G37: 1 | J37: 1.04 | M37: 1 | P37: 1.04 | V37: 1 | Y37: -1 | AE37: 0.5 | AN37: =0.5 -> 0.5
A38: =crop!A38 -> CS #1: faba bean - wheat - rapeseed - maize | B38: =crop!B38 -> C.12.5 | D38: 1.04 | G38: 1 | J38: 1.04 | M38: 1 | P38: 1.04 | V38: 1 | Y38: -1 | AE38: 0.5 | AN38: =0.5 -> 0.5
A39: =crop!A39 -> CS #1: grassland (4 years) - maize - maize | B39: =crop!B39 -> C.12.6 | D39: 1.03 | G39: 1 | J39: 1.03 | M39: 1 | P39: 1.03 | S39: 2 | V39: 1 | AB39: 1 | AE39: 0.5 | AH39: 1 | AK39: 1
A40: =crop!A40 -> CS #1: grassland (3 years) - maize - wheat - barley | B40: =crop!B40 -> C.12.7 | D40: 1.03 | G40: 1 | J40: 1.03 | M40: 1 | P40: 1.03 | S40: 2 | V40: 1 | AB40: 1 | AE40: 0.5 | AH40: 1 | AK40: 1
A41: =crop!A41 -> CS #1: faba bean - wheat - maize - alfalfa (3 years) - barley - maize | B41: =crop!B41 -> C.12.8 | D41: 1.05 | G41: 2 | J41: 1.05 | M41: 2 | P41: 1.05 | S41: 2 | V41: 2 | AB41: 1 | AE41: 0.5 | AH41: 1 | AK41: 1 | AN41: =0.5 -> 0.5
A42: =crop!A42 -> CS #1: grassland (3 years) - maize - wheat - faba bean - rapeseed | B42: =crop!B42 -> C.12.9 | D42: 1.05 | G42: 2 | J42: 1.05 | M42: 2 | P42: 1.05 | S42: 2 | V42: 2 | AB42: 1 | AE42: 0.5 | AH42: 1 | AK42: 1 | AN42: =0.5 -> 0.5
A43: =crop!A43 -> CS #2: maize - wheat | B43: =crop!B43 -> C.13.1 | H43: -1 | Z43: -2
A44: =crop!A44 -> CS #2: rapeseed - wheat - maize - wheat | B44: =crop!B44 -> C.13.2 | E44: 1.02 | K44: 1.02 | Q44: 1.02 | Z44: -2 | AF44: 0.5
A45: =crop!A45 -> CS #2: maize - wheat - maize - barley | B45: =crop!B45 -> C.13.3 | E45: 1.02 | K45: 1.02 | Q45: 1.02 | Z45: -2 | AF45: 0.5
A46: =crop!A46 -> CS #2: alfalfa (3 years) - maize - wheat | B46: =crop!B46 -> C.13.4 | E46: 1.04 | H46: 1 | K46: 1.04 | N46: 1 | Q46: 1.04 | W46: 1 | Z46: -1 | AF46: 0.5 | AO46: =0.5 -> 0.5
A47: =crop!A47 -> CS #2: faba bean - wheat - rapeseed - maize | B47: =crop!B47 -> C.13.5 | E47: 1.04 | H47: 1 | K47: 1.04 | N47: 1 | Q47: 1.04 | W47: 1 | Z47: -1 | AF47: 0.5 | AO47: =0.5 -> 0.5
A48: =crop!A48 -> CS #2: grassland (4 years) - maize - maize | B48: =crop!B48 -> C.13.6 | E48: 1.03 | H48: 1 | K48: 1.03 | N48: 1 | Q48: 1.03 | T48: 2 | W48: 1 | AC48: 1 | AF48: 0.5 | AI48: 1 | AL48: 1
A49: =crop!A49 -> CS #2: grassland (3 years) - maize - wheat - barley | B49: =crop!B49 -> C.13.7 | E49: 1.03 | H49: 1 | K49: 1.03 | N49: 1 | Q49: 1.03 | T49: 2 | W49: 1 | AC49: 1 | AF49: 0.5 | AI49: 1 | AL49: 1
A50: =crop!A50 -> CS #2: faba bean - wheat - maize - alfalfa (3 years) - barley - maize | B50: =crop!B50 -> C.13.8 | E50: 1.05 | H50: 2 | K50: 1.05 | N50: 2 | Q50: 1.05 | T50: 2 | W50: 2 | AC50: 1 | AF50: 0.5 | AI50: 1 | AL50: 1 | AO50: =0.5 -> 0.5
A51: =crop!A51 -> CS #2: grassland (3 years) - maize - wheat - faba bean - rapeseed | B51: =crop!B51 -> C.13.9 | E51: 1.05 | H51: 2 | K51: 1.05 | N51: 2 | Q51: 1.05 | T51: 2 | W51: 2 | AC51: 1 | AF51: 0.5 | AI51: 1 | AL51: 1 | AO51: =0.5 -> 0.5
A52: =crop!A52 -> No particular green infrastructure elements | B52: =crop!B52 -> C.14.1 | D52: =SQRT(0.8) -> 0.89442719 | E52: =SQRT(0.8) -> 0.89442719 | F52: =SQRT(0.8) -> 0.89442719 | J52: =SQRT(0.8) -> 0.89442719 | K52: =SQRT(0.8) -> 0.89442719 | L52: =SQRT(0.8) -> 0.89442719 | P52: =SQRT(0.8) -> 0.89442719 | Q52: =SQRT(0.8) -> 0.89442719 | R52: =SQRT(0.8) -> 0.89442719
A53: =crop!A53 -> Sown field margins as green infrastructures: wildflowers strip | B53: =crop!B53 -> C.14.2 | D53: =1.3/SQRT(0.8) -> 1.4534442 | E53: =1.3/SQRT(0.8) -> 1.4534442 | F53: =1.3/SQRT(0.8) -> 1.4534442 | G53: 0.5 | H53: 0.5 | I53: 0.5 | J53: =1.3/SQRT(0.8) -> 1.4534442 | K53: =1.3/SQRT(0.8) -> 1.4534442 | L53: =1.3/SQRT(0.8) -> 1.4534442 | M53: 0.5 | N53: 0.5 | O53: 0.5 | P53: =1.3/SQRT(0.8) -> 1.4534442 | Q53: =1.3/SQRT(0.8) -> 1.4534442 | R53: =1.3/SQRT(0.8) -> 1.4534442 | AE53: 1 | AF53: 1 | AG53: 1 | AH53: 0.5 | AI53: 0.5 | AK53: 0.5 | AL53: 0.5
A54: =crop!A54 -> Sown field margins as green infrastructures: beetle bank (for birds and polyphagous predator) | B54: =crop!B54 -> C.14.3 | D54: =1.3/SQRT(0.8) -> 1.4534442 | E54: =1.3/SQRT(0.8) -> 1.4534442 | F54: =1.3/SQRT(0.8) -> 1.4534442 | G54: 0.5 | H54: 0.5 | I54: 0.5 | J54: =1.3/SQRT(0.8) -> 1.4534442 | K54: =1.3/SQRT(0.8) -> 1.4534442 | L54: =1.3/SQRT(0.8) -> 1.4534442 | M54: 0.5 | N54: 0.5 | O54: 0.5 | P54: =1.3/SQRT(0.8) -> 1.4534442 | Q54: =1.3/SQRT(0.8) -> 1.4534442 | R54: =1.3/SQRT(0.8) -> 1.4534442 | AE54: 1 | AF54: 1 | AG54: 1 | AH54: 0.5 | AI54: 0.5 | AK54: 0.5 | AL54: 0.5
A55: =crop!A55 -> Semi-natural field margins as green infrastructures: hedgerows | B55: =crop!B55 -> C.14.4 | D55: =1.3/SQRT(0.8) -> 1.4534442 | E55: =1.3/SQRT(0.8) -> 1.4534442 | F55: =1.3/SQRT(0.8) -> 1.4534442 | G55: 1 | H55: 1 | I55: 1 | J55: =1.3/SQRT(0.8) -> 1.4534442 | K55: =1.3/SQRT(0.8) -> 1.4534442 | L55: =1.3/SQRT(0.8) -> 1.4534442 | M55: 0.5 | N55: 0.5 | O55: 0.5 | P55: =1.3/SQRT(0.8) -> 1.4534442 | Q55: =1.3/SQRT(0.8) -> 1.4534442 | R55: =1.3/SQRT(0.8) -> 1.4534442 | AE55: 1 | AF55: 1 | AG55: 1 | AH55: 1 | AI55: 1 | AK55: 1 | AL55: 1 | AN55: =0.5 -> 0.5 | AO55: =0.5 -> 0.5
A56: =crop!A56 -> Semi-natural field margins as green infrastructures: grass margins | B56: =crop!B56 -> C.14.5 | D56: =1.3/SQRT(0.8) -> 1.4534442 | E56: =1.3/SQRT(0.8) -> 1.4534442 | F56: =1.3/SQRT(0.8) -> 1.4534442 | G56: 1 | H56: 1 | I56: 1 | J56: =1.3/SQRT(0.8) -> 1.4534442 | K56: =1.3/SQRT(0.8) -> 1.4534442 | L56: =1.3/SQRT(0.8) -> 1.4534442 | M56: 0.5 | N56: 0.5 | O56: 0.5 | P56: =1.3/SQRT(0.8) -> 1.4534442 | Q56: =1.3/SQRT(0.8) -> 1.4534442 | R56: =1.3/SQRT(0.8) -> 1.4534442 | AE56: 1 | AF56: 1 | AG56: 1 | AH56: 0.5 | AI56: 0.5 | AK56: 0.5 | AL56: 0.5
A57: =crop!A57 -> No agroforestry | B57: =crop!B57 -> C.15.1 | D57: =SQRT(0.8) -> 0.89442719 | E57: 0.89442719 | F57: 0.89442719 | J57: =SQRT(0.8) -> 0.89442719 | K57: 0.89442719 | L57: 0.89442719 | P57: =SQRT(0.8) -> 0.89442719 | Q57: 0.89442719 | R57: 0.89442719
A58: =crop!A58 -> In-field agroforestry | B58: =crop!B58 -> C.15.2 | D58: =1.3/SQRT(0.8) -> 1.4534442 | E58: =1.3/SQRT(0.8) -> 1.4534442 | F58: =1.3/SQRT(0.8) -> 1.4534442 | G58: 1 | H58: 1 | I58: 1 | J58: =1.3/SQRT(0.8) -> 1.4534442 | K58: =1.3/SQRT(0.8) -> 1.4534442 | L58: =1.3/SQRT(0.8) -> 1.4534442 | M58: 0.5 | N58: 0.5 | O58: 0.5 | P58: =1.3/SQRT(0.8) -> 1.4534442 | Q58: =1.3/SQRT(0.8) -> 1.4534442 | R58: =1.3/SQRT(0.8) -> 1.4534442 | AE58: 1 | AF58: 1 | AG58: 1 | AH58: 1 | AI58: 1 | AK58: 0.5 | AL58: 0.5
A59: =crop!A59 -> Balanced strategy between farmer income and investment | B59: =crop!B59 -> E.1.1
A60: =crop!A60 -> Investment-oriented strategy | B60: =crop!B60 -> E.1.2
A61: =crop!A61 -> Income-oriented strategy | B61: =crop!B61 -> E.1.3
A62: =crop!A62 -> Conventional farming | B62: =crop!B62 -> G.1.1
A63: =crop!A63 -> Organic farming | B63: =crop!B63 -> G.1.2 | G63: 0.5 | H63: 0.5 | I63: 0.5 | M63: 0.5 | N63: 0.5 | O63: 0.5 | V63: 1 | W63: 1 | X63: 1 | Y63: -0.5 | Z63: -0.5 | AA63: -0.5
A64: =crop!A64 -> Cattle breed is Holstein | B64: =crop!B64 -> A.1.1
A65: =crop!A65 -> Cattle breed is Siemmental | B65: =crop!B65 -> A.1.2
A66: =crop!A66 -> Cattle breed is Montbéliarde | B66: =crop!B66 -> A.1.3
A67: =crop!A67 -> Initial herd size | B67: =crop!B67 -> A.2.1
A68: =crop!A68 -> 15% increase of initial herd size (no building modification) | B68: =crop!B68 -> A.2.2
A69: =crop!A69 -> 15% increase of initial herd size (building modification) | B69: =crop!B69 -> A.2.3
A70: =crop!A70 -> 30% increase of initial herd size (building modification) | B70: =crop!B70 -> A.2.4
A71: =crop!A71 -> 15% decrease of initial herd size | B71: =crop!B71 -> A.2.5
A72: =crop!A72 -> 30% decrease of initial herd size | B72: =crop!B72 -> A.2.6
A73: =crop!A73 -> Bulls fattened up to 18 months | B73: =crop!B73 -> A.3.1
A74: =crop!A74 -> Castrated males fattened up to 36 months (steer) | B74: =crop!B74 -> A.3.2
A75: =crop!A75 -> Male calves sold at 8 days | B75: =crop!B75 -> A.3.3
A76: =crop!A76 -> Cows are tied on straw bedding | B76: =crop!B76 -> A.4.1 | D76: =SQRT(1.1) -> 1.0488088 | E76: =SQRT(1.1) -> 1.0488088 | F76: =SQRT(1.1) -> 1.0488088 | J76: =SQRT(1.1) -> 1.0488088 | K76: =SQRT(1.1) -> 1.0488088 | L76: =SQRT(1.1) -> 1.0488088
A77: =crop!A77 -> Housing of cows is cubicles with straw (shallow bedding) | B77: =crop!B77 -> A.4.2 | D77: =SQRT(1.1) -> 1.0488088 | E77: =SQRT(1.1) -> 1.0488088 | F77: =SQRT(1.1) -> 1.0488088 | J77: =SQRT(1.1) -> 1.0488088 | K77: =SQRT(1.1) -> 1.0488088 | L77: =SQRT(1.1) -> 1.0488088
A78: =crop!A78 -> Housing of cows is cubicles with slatted floor | B78: =crop!B78 -> A.4.3 | D78: =SQRT(1.02) -> 1.0099505 | E78: =SQRT(1.02) -> 1.0099505 | F78: =SQRT(1.02) -> 1.0099505 | J78: =SQRT(1.02) -> 1.0099505 | K78: =SQRT(1.02) -> 1.0099505 | L78: =SQRT(1.02) -> 1.0099505
A79: =crop!A79 -> Housing of cows is free-stall (deep bedding) | B79: =crop!B79 -> A.4.4 | D79: =SQRT(1.02) -> 1.0099505 | E79: =SQRT(1.02) -> 1.0099505 | F79: =SQRT(1.02) -> 1.0099505 | J79: =SQRT(1.02) -> 1.0099505 | K79: =SQRT(1.02) -> 1.0099505 | L79: =SQRT(1.02) -> 1.0099505
A80: =crop!A80 -> Housing of cows is free-stall slatted floor | B80: =crop!B80 -> A.4.5 | D80: =SQRT(1.02) -> 1.0099505 | E80: =SQRT(1.02) -> 1.0099505 | F80: =SQRT(1.02) -> 1.0099505 | J80: =SQRT(1.02) -> 1.0099505 | K80: =SQRT(1.02) -> 1.0099505 | L80: =SQRT(1.02) -> 1.0099505
A81: =crop!A81 -> Housing of heifer, bulls and steers is slatted floor | B81: =crop!B81 -> A.5.1 | D81: =SQRT(1.02) -> 1.0099505 | E81: =SQRT(1.02) -> 1.0099505 | F81: =SQRT(1.02) -> 1.0099505 | J81: =SQRT(1.02) -> 1.0099505 | K81: =SQRT(1.02) -> 1.0099505 | L81: =SQRT(1.02) -> 1.0099505
A82: =crop!A82 -> Housing of heifer, bulls and steers is shallow bedding | B82: =crop!B82 -> A.5.2 | D82: =SQRT(1.1) -> 1.0488088 | E82: =SQRT(1.1) -> 1.0488088 | F82: =SQRT(1.1) -> 1.0488088 | J82: =SQRT(1.1) -> 1.0488088 | K82: =SQRT(1.1) -> 1.0488088 | L82: =SQRT(1.1) -> 1.0488088
A83: =crop!A83 -> Housing of heifer, bulls and steers is deep bedding | B83: =crop!B83 -> A.5.3 | D83: =SQRT(1.1) -> 1.0488088 | E83: =SQRT(1.1) -> 1.0488088 | F83: =SQRT(1.1) -> 1.0488088 | J83: =SQRT(1.1) -> 1.0488088 | K83: =SQRT(1.1) -> 1.0488088 | L83: =SQRT(1.1) -> 1.0488088
A84: =crop!A84 -> Cow feeding system: all year indoor, maize silage & soybean meal supplement | B84: =crop!B84 -> A.6.1
A85: =crop!A85 -> Cow feeding system: all year indoor, sorghum silage & soybean meal supplement | B85: =crop!B85 -> A.6.2
A86: =crop!A86 -> Cow feeding system: all year indoor, sorghum & alfalfa silage | B86: =crop!B86 -> A.6.3
A87: =crop!A87 -> Cow feeding system: all year indoor, maize silage, alfalfa silage & soybean meal supplement | B87: =crop!B87 -> A.6.4
A88: =crop!A88 -> Cow feeding system: 4 months grazing & soybean meal supplement | B88: =crop!B88 -> A.6.5
A89: =crop!A89 -> Cow feeding system: 4 months grazing & rapeseed meal supplement | B89: =crop!B89 -> A.6.6
A90: =crop!A90 -> Cow feeding system: 5 months grazing & rapeseed meal supplement | B90: =crop!B90 -> A.6.7
A91: =crop!A91 -> Cow feeding system: 7 months grazing & rapeseed meal supplement | B91: =crop!B91 -> A.6.8
A92: =crop!A92 -> Cow feeding system: 8 months grazing & faba bean supplement | B92: =crop!B92 -> A.6.9
A93: =crop!A93 -> Cow feeding system: all year indoor, hay & rapeseed meal supplement | B93: =crop!B93 -> A.6.10
A94: =crop!A94 -> Cow feeding system: 9 months grazing, without protein feed supplement | B94: =crop!B94 -> A.6.11
A95: =crop!A95 -> No concentrate supply for lactating dairy cows | B95: =crop!B95 -> A.7.1
... A109: =crop!A109 -> Preventive measures of hygiene of the housing conditions (no treatment of cows) | B109: =crop!B109 -> A.9.3
A110: =crop!A110 -> Systematic anti-parasitic treatment of heifers | B110: =crop!B110 -> A.10.1 | J110: 0.92 | K110: 0.92 | L110: 0.92
A111: =crop!A111 -> Selective/targeted treatment of heifers shedding high amounts of parasites | B111: =crop!B111 -> A.10.2 | J111: 0.96 | K111: 0.96 | L111: 0.96
A112: =crop!A112 -> Immunization against internal parasites by low exposure grazing of heifers (no treatment) | B112: =crop!B112 -> A.10.3
A113: =crop!A113 -> Milk replacer is fed to calves | B113: =crop!B113 -> A.11.1
...

Sheet animal
C1: Name of the indicator | D1: Average number of dairy cows | E1: Average number of heifers | F1: Average number of bulls and steers | G1: Average number of calves | H1: Number of culled cows sold | I1: Number of bulls and steers sold | J1: Number of calves sold | K1: Number of non pregnant heifers sold | L1: Number of pregnant heifers sold | M1: Cow culling rate | N1: Heifer conception rate | O1: Cow calving rate | P1: Calf mortality | Q1: Young cattle mortality | R1: Option for herd size | S1: Meat of culled cows | T1: Meat of bulls and steers | U1: Meat of non pregnant heifers | V1: Milk production per dairy cow | W1: Fat content | X1: Protein content | Y1: Somatic cells count | Z1: Animal welfare of cows | AA1: Animal welfare of heifers | AB1: Animal welfare of bulls | AC1: Animal welfare of steers | AD1: Antibiotic use for cows | AE1: Antibiotic use for heifers | AF1: Antibiotic use for bulls | AG1: Antibiotic use for steers | AH1: Anthelmintic use for cows | AI1: Anthelmintic use for heifers | AJ1: Anthelmintic use for bulls | AK1: Anthelmintic use for steers | AL1: Veterinary costs for cows | AM1: Veterinary costs for heifers | AN1: Veterinary costs for bulls | AO1: Veterinary costs for steers | AP1: Insemination costs | AQ1: Water demand for cows | AR1: Water demand for heifers | AS1: Water demand for pregnant heifers | AT1: Water demand for bulls and steers | AU1: Water demand for calves | AV1: Water demand for other uses | AW1: Straw demand for cows | AX1: Straw demand for heifers | AY1: Straw demand for bulls | AZ1: Straw demand for steers | BA1: Manure production of cows | BB1: Manure production of heifers | BC1: Manure production of bulls | BD1: Manure production of steers | BE1: Slurry production of cows | BF1: Slurry production of heifers | BG1: Slurry production of bulls | BH1: Slurry production of steers | BI1: Number of days of grazing | BJ1: Maize silage demand for cows | BK1: Maize silage demand for heifers | BL1: Maize silage demand for bulls | BM1: Maize silage demand for steers | BN1: Grass silage demand for cows | BO1: Grass silage demand for heifers | BP1: Grass silage demand for bulls | BQ1: Grass silage demand for steers | BR1: Alfalfa silage demand for cows | BS1: Alfalfa silage demand for heifers | BT1: Alfalfa silage demand for bulls | BU1: Alfalfa silage demand for steers | BV1: Sorghum silage demand for cows | BW1: Sorghum silage demand for heifers | BX1: Sorghum silage demand for bulls | BY1: Sorghum silage demand for steers | BZ1: Hay demand for cows | CA1: Hay demand for heifers | CB1: Hay demand for bulls | CC1: Hay demand for steers | CD1: Grazed grass demand for cows | CE1: Grazed grass demand for heifers | CF1: Grazed grass demand for bulls | CG1: Grazed grass demand for steers | CH1: Barley demand for cows | CI1: Barley demand for heifers | CJ1: Barley demand for bulls | CK1: Barley demand for steers | CL1: RSM demand for cows | CM1: RSM demand for heifers | CN1: RSM demand for bulls | CO1: RSM demand for steers | CP1: SBM demand for cows | CQ1: SBM demand for heifers | CR1: SBM demand for bulls | CS1: SBM demand for steers | CT1: Faba bean demand for cows | CU1: Faba bean demand for heifers | CV1: Faba bean demand for bulls | CW1: Faba bean demand for steers | CX1: Wheat demand for cows | CY1: Wheat demand for heifers | CZ1: Wheat demand for bulls | DA1: Wheat demand for steers | DB1: Milk replacer demand for cows | DC1: Milk replacer demand for heifers | DD1: Milk replacer demand for bulls | DE1: Milk replacer demand for steers | DF1: Milk demand for cows | DG1: Milk demand for heifers | DH1: Milk demand for bulls | DI1: Milk demand for steers | DJ1: Feed straw demand for cows | DK1: Feed straw demand for heifers | DL1: Feed straw demand for bulls | DM1: Feed straw demand for steers | DN1: Intermediate indicator for indF59 - manure production of cows | DO1: Intermediate indicator for indF59 - manure production of heifers | DP1: Intermediate indicator for indF59 - manure production of bulls | DQ1: Intermediate indicator for indF59 - manure production of steers | DR1: Intermediate indicator for indF59 - slurry production of cows | DS1: Intermediate indicator for indF59 - slurry production of heifers | DT1: Intermediate indicator for indF59 - slurry production of bulls | DU1: Intermediate indicator for indF59 - slurry production of steers
A2: AEP name | B2: AEP_ID | C2: IndicatorID | D2: =INDEX([1]indicators!$I$2:$I$1491,MATCH(D$1,[1]indicators!$C$2:$C$1491,0),1) -> indAn1 | E2: =INDEX([1]indicators!$I$2:$I$1491,MATCH(E$1,[1]indicators!$C$2:$C$1491,0),1) -> indAn2 | F2: =INDEX([1]indicators!$I$2:$I$1491,MATCH(F$1,[1]indicators!$C$2:$C$1491,0),1) -> indAn3 | G2: =INDEX([1]indicators!$I$2:$I$1491,MATCH(G$1,[1]indicators!$C$2:$C$1491,0),1) -> indAn4 | H2: =INDEX([1]indicators!$I$2:$I$1491,MATCH(H$1,[1]indicators!$C$2:$C$1491,0),1) -> indAn5 | I2: =INDEX([1]indicators!$I$2:$I$1491,MATCH(I$1,[1]indicators!$C$2:$C$1491,0),1) -> indAn6 | J2: =INDEX([1]indicators!$I$2:$I$1491,MATCH(J$1,[1]indicators!$C$2:$C$1491,0),1) -> indAn7 | K2: =INDEX([1]indicators!$I$2:$I$1491,MATCH(K$1,[1]indicators!$C$2:$C$1491,0),1) -> indAn8 | ... DU2: =INDEX([1]indicators!$I$2:$I$1491,MATCH(DU$1,[1]indicators!$C$2:$C$1491,0),1) -> indF106
A3: =crop!A3 -> Conventional tillage (CT) | B3: =crop!B3 -> C.1.1
A4: =crop!A4 -> Reduced tillage (RT) | B4: =crop!B4 -> C.1.2
A5: =crop!A5 -> No tillage (NT) | B5: =crop!B5 -> C.1.3
A6: =crop!A6 -> Fall cover crop destructed before winter | B6: =crop!B6 -> C.2.1
A7: =crop!A7 -> Fall cover crop destructed early spring | B7: =crop!B7 -> C.2.2
A8: =crop!A8 -> Permanent soil cover | B8: =crop!B8 -> C.2.3
A9: =crop!A9 -> Straw removal | B9: =crop!B9 -> C.3.1
A10: =crop!A10 -> Straw left on soil | B10: =crop!B10 -> C.3.2
A11: =crop!A11 -> On-farm organic fertilizers + input of mineral fertilizer | B11: =crop!B11 -> C.4.1
A12: =crop!A12 -> On-farm organic fertilizers only | B12: =crop!B12 -> C.4.2
A13: =crop!A13 -> Systematic use of chemical fungicides | B13: =crop!B13 -> C.5.1
A14: =crop!A14 -> Sound approach of chemical fungicides | B14: =crop!B14 -> C.5.2
... A64: =crop!A64 -> Cattle breed is Holstein | B64: =crop!B64 -> A.1.1
A65: =crop!A65 -> Cattle breed is Siemmental | B65: =crop!B65 -> A.1.2 | M65: 0.95 | N65: 1.05 | O65: 1.03 | Q65: 0.97 | S65: 1.06 | T65: 1.15 | U65: 1.14 | V65: 0.75 | W65: 1.05 | X65: 1.03 | Y65: 1.04 | AD65: 1.04 | AL65: 0.9 | AM65: 0.8 | AN65: 0.8 | AO65: 0.8 | AP65: 0.9
A66: =crop!A66 -> Cattle breed is Montbéliarde | B66: =crop!B66 -> A.1.3 | M66: 0.95 | N66: 1.05 | O66: 1.03 | Q66: 0.97 | S66: 1.06 | T66: 1.15 | U66: 1.14 | V66: 0.88 | W66: 1.02 | X66: 1.05 | Y66: 1.04 | AD66: 1.04 | AL66: 0.9 | AM66: 0.8 | AN66: 0.8 | AO66: 0.8 | AP66: 0.9
A67: =crop!A67 -> Initial herd size | B67: =crop!B67 -> A.2.1
A68: =crop!A68 -> 15% increase of initial herd size (no building modification) | B68: =crop!B68 -> A.2.2 | M68: 1.03 | O68: 0.98 | R68: 1.15 | Y68: 1.02 | Z68: 0.9 | AA68: 0.9 | AB68: 0.9 | AC68: 0.9 | AD68: 1.1 | AE68: 1.1 | AF68: 1.1 | AG68: 1.1 | AL68: 1.05 | AM68: 1.03 | AN68: 1.03 | AO68: 1.03
A69: =crop!A69 -> 15% increase of initial herd size (building modification) | B69: =crop!B69 -> A.2.3 | R69: 1.15
A70: =crop!A70 -> 30% increase of initial herd size (building modification) | B70: =crop!B70 -> A.2.4 | R70: 1.3
A71: =crop!A71 -> 15% decrease of initial herd size | B71: =crop!B71 -> A.2.5 | R71: 0.85 | Y71: 0.98 | Z71: 1.1 | AA71: 1.1 | AB71: 1.1 | AC71: 1.1 | AD71: 0.97 | AE71: 0.97 | AF71: 0.97 | AG71: 0.97 | AL71: 0.95 | AM71: 0.97 | AN71: 0.97 | AO71: 0.97
A72: =crop!A72 -> 30% decrease of initial herd size | B72: =crop!B72 -> A.2.6 | R72: 0.7 | Y72: 0.98 | Z72: 1.1 | AA72: 1.1 | AB72: 1.1 | AC72: 1.1 | AD72: 0.97 | AE72: 0.97 | AF72: 0.97 | AG72: 0.97 | AL72: 0.95 | AM72: 0.97 | AN72: 0.97 | AO72: 0.97
A73: =crop!A73 -> Bulls fattened up to 18 months | B73: =crop!B73 -> A.3.1 | J73: 0 | AC73: 0 | AG73: 0 | AK73: 0 | AO73: 0 | AZ73: 0 | BD73: 0 | BH73: 0 | BL73: 3 | BM73: 0 | BP73: 0 | BQ73: 0 | BT73: 0 | BU73: 0 | BX73: 0 | BY73: 0 | CB73: 0.1 | CC73: 0 | CF73: 0 | CG73: 0 | CJ73: 0 | CK73: 0 | CN73: 0 | CO73: 0 | CR73: 0.42 | CS73: 0 | CV73: 0 | CW73: 0 | CZ73: 0.4 | DA73: 0 | DL73: 0 | DM73: 0 | DQ73: 0 | DU73: 0
A74: =crop!A74 -> Castrated males fattened up to 36 months (steer) | B74: =crop!B74 -> A.3.2 | F74: 2.5 | J74: 0 | T74: 1.07 | AB74: 0 | AF74: 0 | AJ74: 0 | AN74: 0 | AY74: 0 | AZ74: 0.5 | BC74: 0 | BG74: 0 | BL74: 0 | BM74: 0 | BP74: 0 | BQ74: 0 | BT74: 0 | BU74: 0 | BX74: 0 | BY74: 0 | CB74: 0 | CC74: 2.5 | CF74: 0 | CG74: 3.4 | CJ74: 0 | CK74: 0 | CN74: 0 | CO74: 0 | CR74: 0 | CS74: 0.06 | CV74: 0 | CW74: 0 | CZ74: 0 | DA74: 0.3 | DL74: 0 | DM74: 0 | DP74: 0 | DT74: 0
A75: =crop!A75 -> Male calves sold at 8 days | B75: =crop!B75 -> A.3.3 | F75: 0 | I75: 0 | T75: 0 | AB75: 0 | AC75: 0 | AF75: 0 | AG75: 0 | AJ75: 0 | AK75: 0 | AN75: 0 | AO75: 0 | AT75: 0 | AU75: 0 | AY75: 0 | AZ75: 0 | BC75: 0 | BD75: 0 | BG75: 0 | BH75: 0 | BL75: 0 | BM75: 0 | BP75: 0 | BQ75: 0 | BT75: 0 | BU75: 0 | BX75: 0 | BY75: 0 | CB75: 0 | CC75: 0 | CF75: 0 | CG75: 0 | CJ75: 0 | CK75: 0 | CN75: 0 | CO75: 0 | CR75: 0 | CS75: 0 | CV75: 0 | CW75: 0 | CZ75: 0 | DA75: 0 | DL75: 0 | DM75: 0 | DP75: 0 | DQ75: 0 | DT75: 0 | DU75: 0
A76: =crop!A76 -> Cows are tied on straw bedding | B76: =crop!B76 -> A.4.1 | AV76: 14 | BE76: 0 | DR76: 0
A77: =crop!A77 -> Housing of cows is cubicles with straw (shallow bedding) | B77: =crop!B77 -> A.4.2 | M77: 0.98 | O77: 1.02 | P77: 0.97 | Q77: 0.98 | V77: 1.01 | Y77: 0.98 | Z77: 1.5 | AD77: 0.98 | AL77: 0.67 | AP77: 0.9 | AQ77: 1.05 | AV77: 17 | BE77: 0 | DR77: 0
A78: =crop!A78 -> Housing of cows is cubicles with slatted floor | B78: =crop!B78 -> A.4.3 | M78: 1.03 | O78: 0.97 | P78: 1.05 | Q78: 1.03 | Y78: 1.03 | Z78: 1.13 | AD78: 1.03 | AL78: 0.67 | AP78: 0.9 | AQ78: 1.05 | AV78: 17 | AW78: 0 | BA78: 0 | DN78: 0
A79: =crop!A79 -> Housing of cows is free-stall (deep bedding) | B79: =crop!B79 -> A.4.4 | M79: 0.98 | O79: 1.03 | P79: 0.95 | Q79: 0.97 | V79: 1.03 | Y79: 1.02 | Z79: 1.65 | AD79: 1.02 | AL79: 0.6 | AP79: 0.81 | AQ79: 1.05 | AV79: 17 | AW79: 1.6 | BA79: 1.1 | BE79: 0 | DN79: 1.1 | DR79: 0
A80: =crop!A80 -> Housing of cows is free-stall slatted floor | B80: =crop!B80 -> A.4.5 | M80: 1.03 | O80: 0.97 | P80: 1.03 | Q80: 1.02 | V80: 0.98 | Y80: 1.03 | Z80: 1.2 | AD80: 1.03 | AL80: 0.6 | AP80: 0.91 | AQ80: 1.05 | AV80: 17 | AW80: 0 | BA80: 0 | DN80: 0
A81: =crop!A81 -> Housing of heifer, bulls and steers is slatted floor | B81: =crop!B81 -> A.5.1 | N81: 0.97 | AX81: 0 | AY81: 0 | AZ81: 0 | BB81: 0 | BC81: 0 | BD81: 0 | DO81: 0 | DP81: 0 | DQ81: 0
A82: =crop!A82 -> Housing of heifer, bulls and steers is shallow bedding | B82: =crop!B82 -> A.5.2 | N82: 1.03 | AA82: 1.61 | AB82: 1.61 | AC82: 1.61 | AM82: 0.8 | AN82: 0.8 | AO82: 0.8 | BF82: 0 | BG82: 0 | BH82: 0 | DS82: 0 | DT82: 0 | DU82: 0
A83: =crop!A83 -> Housing of heifer, bulls and steers is deep bedding | B83: =crop!B83 -> A.5.3 | AA83: 2.01 | AB83: 2.01 | AC83: 2.01 | AM83: 0.5 | AN83: 0.5 | AO83: 0.5 | AX83: 1.6 | AY83: 1.6 | AZ83: 1.6 | BB83: 1.1 | BC83: 1.1 | BD83: 1.1 | BF83: 0 | BG83: 0 | BH83: 0 | DO83: 1.1 | DP83: 1.1 | DQ83: 1.1 | DS83: 0 | DT83: 0 | DU83: 0
A84: =crop!A84 -> Cow feeding system: all year indoor, maize silage & soybean meal supplement | B84: =crop!B84 -> A.6.1 | AH84: 0 | BI84: 0 | BJ84: 5.11 | BN84: 0 | BR84: 0 | BV84: 0 | BZ84: 0.4 | CD84: 0 | CH84: 0 | CL84: 0 | CP84: 0.91 | CT84: 0 | CX84: 1.1 | DJ84: 0
A85: =crop!A85 -> Cow feeding system: all year indoor, sorghum silage & soybean meal supplement | B85: =crop!B85 -> A.6.2 | AH85: 0 | BI85: 0 | BJ85: 0 | BN85: 0 | BR85: 0 | BV85: 3.29 | BZ85: 0.73 | CD85: 0 | CH85: 0 | CL85: 0 | CP85: 0.37 | CT85: 0 | CX85: 3.29 | DJ85: 0
A86: =crop!A86 -> Cow feeding system: all year indoor, sorghum & alfalfa silage | B86: =crop!B86 -> A.6.3 | AH86: 0 | BI86: 0 | BJ86: 0 | BN86: 0 | BR86: 1.83 | BV86: 2.19 | BZ86: 0.44 | CD86: 0 | CH86: 0 | CL86: 0 | CP86: 0 | CT86: 0 | CX86: 3.5 | DJ86: 0
A87: =crop!A87 -> Cow feeding system: all year indoor, maize silage, alfalfa silage & soybean meal supplement | B87: =crop!B87 -> A.6.4 | AH87: 0 | BI87: 0 | BJ87: 2.56 | BN87: 0 | BR87: 2.37 | BV87: 0 | BZ87: 0.44 | CD87: 0 | CH87: 0 | CL87: 0 | CP87: 0.15 | CT87: 0 | CX87: 2.19 | DJ87: 0
A88: =crop!A88 -> Cow feeding system: 4 months grazing & soybean meal supplement | B88: =crop!B88 -> A.6.5 | M88: 0.98 | O88: 1.02 | P88: 0.97 | Q88: 0.98 | V88: 0.94 | W88: 0.95 | X88: 0.93 | Z88: 1.31 | AL88: 0.76 | AP88: 0.84 | AQ88: 0.94 | AW88: =1-(24/24*4/12) -> 0.66666667 | BA88: =1-(24/24*4/12) -> 0.66666667 | BE88: =1-(24/24*4/12) -> 0.66666667 | BI88: =4/12*365 -> 121.66667 | BJ88: 4.27 | BN88: 0 | BR88: 0 | BV88: 0 | BZ88: 0.5 | CD88: 0.84 | CH88: 0 | CL88: 0 | CP88: 0.62 | CT88: 0 | CX88: 1.03 | DJ88: 0 | DN88: =1-(24/24*4/12) -> 0.66666667 | DR88: =1-(24/24*4/12) -> 0.66666667
A89: =crop!A89 -> Cow feeding system: 4 months grazing & rapeseed meal supplement | B89: =crop!B89 -> A.6.6 | M89: 0.98 | O89: 1.02 | P89: 0.97 | Q89: 0.98 | V89: 0.94 | W89: 0.95 | X89: 0.93 | Z89: 1.31 | AL89: 0.76 | AP89: 0.84 | AQ89: 0.94 | AW89: =1-(24/24*4/12) -> 0.66666667 | BA89: =1-(24/24*4/12) -> 0.66666667 | BE89: =1-(24/24*4/12) -> 0.66666667 | BI89: =4/12*365 -> 121.66667 | BJ89: 2.56 | BN89: 1.72 | BR89: 0 | BV89: 0 | BZ89: 0.18 | CD89: 0.84 | CH89: 0 | CL89: 0.55 | CP89: 0 | CT89: 0 | CX89: 1.77 | DJ89: 0 | DN89: =1-(24/24*4/12) -> 0.66666667 | DR89: =1-(24/24*4/12) -> 0.66666667
A90: =crop!A90 -> Cow feeding system: 5 months grazing & rapeseed meal supplement | B90: =crop!B90 -> A.6.7 | M90: 0.98 | O90: 1.02 | P90: 0.97 | Q90: 0.98 | V90: 0.88 | W90: 0.94 | X90: 0.92 | Y90: 0.95 | Z90: 1.39 | AD90: 0.95 | AL90: 0.72 | AP90: 0.76 | AQ90: 0.88 | AW90: =1-(24/24*5/12) -> 0.58333333 | BA90: =1-(24/24*5/12) -> 0.58333333 | BE90: =1-(24/24*5/12) -> 0.58333333 | BI90: =5/12*365 -> 152.08333 | BJ90: 1.68 | BN90: 1.47 | BR90: 0 | BV90: 0 | BZ90: 0.14 | CD90: 2.33 | CH90: 0 | CL90: 0.48 | CP90: 0 | CT90: 0 | CX90: 1.04 | DJ90: 0 | DN90: =1-(24/24*5/12) -> 0.58333333 | DR90: =1-(24/24*5/12) -> 0.58333333
A91: =crop!A91 -> Cow feeding system: 7 months grazing & rapeseed meal supplement | B91: =crop!B91 -> A.6.8 | M91: 0.95 | O91: 1.05 | P91: 0.95 | Q91: 0.96 | V91: 0.88 | W91: 0.94 | X91: 0.92 | Y91: 0.93 | Z91: 1.55 | AD91: 0.93 | AL91: 0.65 | AP91: 0.76 | AQ91: 0.88 | AW91: =1-(24/24*7/12) -> 0.41666667 | BA91: =1-(24/24*7/12) -> 0.41666667 | BE91: =1-(24/24*7/12) -> 0.41666667 | BI91: =7/12*365 -> 212.91667 | BJ91: 1.87 | BN91: 1.09 | BR91: 0 | BV91: 0 | BZ91: 0.27 | CD91: 2.43 | CH91: 0 | CL91: 0.43 | CP91: 0 | CT91: 0 | CX91: 1.08 | DJ91: 0 | DN91: =1-(24/24*7/12) -> 0.41666667 | DR91: =1-(24/24*7/12) -> 0.41666667
A92: =crop!A92 -> Cow feeding system: 8 months grazing & faba bean supplement | B92: =crop!B92 -> A.6.9 | M92: 0.95 | O92: 1.05 | P92: 0.95 | Q92: 0.96 | V92: 0.82 | W92: 0.93 | X92: 0.91 | Y92: 0.92 | Z92: 1.63 | AD92: 0.92 | AL92: 0.61 | AP92: 0.67 | AQ92: 0.82 | AW92: =1-(24/24*8/12) -> 0.33333333 | BA92: =1-(24/24*8/12) -> 0.33333333 | BE92: =1-(24/24*8/12) -> 0.33333333 | BI92: =8/12*365 -> 243.33333 | BJ92: 0.88 | BN92: 1.72 | BR92: 0 | BV92: 0 | BZ92: 0.36 | CD92: 2.64 | CH92: 0 | CL92: 0 | CP92: 0 | CT92: 0.18 | CX92: 1.32 | DJ92: 0 | DN92: =1-(24/24*8/12) -> 0.33333333 | DR92: =1-(24/24*8/12) -> 0.33333333
A93: =crop!A93 -> Cow feeding system: all year indoor, hay & rapeseed meal supplement | B93: =crop!B93 -> A.6.10 | V93: 0.76 | Y93: 0.99 | AD93: 0.99 | AH93: 0 | AP93: 0.74 | AQ93: 0.76 | BI93: 0 | BJ93: 0 | BN93: 0 | BR93: 0 | BV93: 0 | BZ93: 5.29 | CD93: 0 | CH93: 0 | CL93: 0.15 | CP93: 0 | CT93: 0 | CX93: 1.28 | DJ93: 0
A94: =crop!A94 -> Cow feeding system: 9 months grazing, without protein feed supplement | B94: =crop!B94 -> A.6.11 | M94: 0.95 | O94: 1.05 | P94: 0.95 | Q94: 0.96 | V94: 0.76 | W94: 0.92 | X94: 0.9 | Y94: 0.92 | Z94: 1.7 | AD94: 0.92 | AL94: 0.59 | AP94: 0.67 | AQ94: 0.76 | AW94: =1-(24/24*9/12) -> 0.25 | BA94: =1-(24/24*9/12) -> 0.25 | BE94: =1-(24/24*9/12) -> 0.25 | BI94: =9/12*365 -> 273.75 | BJ94: 0 | BN94: 2.35 | BR94: 0 | BV94: 0 | BZ94: 0.26 | CD94: 3.16 | CH94: 0 | CL94: 0 | CP94: 0 | CT94: 0 | CX94: 0.94 | DJ94: 0 | DN94: =1-(24/24*9/12) -> 0.25 | DR94: =1-(24/24*9/12) -> 0.25
A95: =crop!A95 -> No concentrate supply for lactating dairy cows | B95: =crop!B95 -> A.7.1 | BJ95: 0 | BV95: 0 | BZ95: 0 | CD95: 0
A96: =crop!A96 -> +1000 kg / cow / year with soybean meal and cereals | B96: =crop!B96 -> A.7.2 | M96: 1.05 | N96: 0.98 | O96: 0.95 | P96: 1.02 | V96: 900 | Y96: 0.08 | Z96: 0.98 | AD96: 0.08 | AL96: 1.02 | AP96: 0.34 | AQ96: 3500 | BJ96: -1 | BV96: -1 | BZ96: -1 | CD96: -1 | CP96: =400/1000 -> 0.4 | CX96: =1600/1000 -> 1.6
A97: =crop!A97 -> +500 kg / cow / year with soybean meal and cereals | B97: =crop!B97 -> A.7.3 | M97: 1.03 | O97: 0.98 | V97: 450 | Y97: 0.04 | Z97: 0.99 | AD97: 0.04 | AL97: 1.01 | AP97: 0.17 | AQ97: 1750 | BJ97: -0.5 | BV97: -0.5 | BZ97: -0.5 | CD97: -0.5 | CP97: =200/1000 -> 0.2 | CX97: =800/1000 -> 0.8
A98: =crop!A98 -> +500 kg / cow / year with faba bean and cereals | B98: =crop!B98 -> A.7.4 | M98: 1.03 | O98: 0.98 | V98: 450 | Y98: 0.04 | Z98: 0.99 | AD98: 0.04 | AL98: 1.01 | AP98: 0.17 | AQ98: 1750 | BJ98: -0.6 | BV98: -0.6 | BZ98: -0.6 | CD98: -0.6 | CT98: =400/1000 -> 0.4 | CX98: =800/1000 -> 0.8
A99: =crop!A99 -> Heifer feeding system: zero grazing / maize silage + soybean meal | Age at first calving: 24 months | B99: =crop!B99 -> A.8.1 | AI99: 0 | BD99: 0.5 | BH99: 0.5 | BK99: 3.8 | BO99: 0 | BS99: 0 | BW99: 0 | CA99: 1.5 | CE99: 0 | CI99: 0 | CM99: 0 | CQ99: 0.83 | CU99: 0 | CY99: 0.05 | DK99: 0.2 | DQ99: 0.5 | DU99: 0.5
A100: =crop!A100 -> Heifer feeding system: 4 months grazing / 8 months maize silage + hay + soybean meal | Age at first calving: 24 months | B100: =crop!B100 -> A.8.2 | M100: 0.98 | N100: 1.02 | Q100: 0.98 | AA100: 1.55 | AM100: 0.95 | AP100: 0.98 | AX100: 0.79 | BB100: 0.83 | BD100: 0.5 | BF100: 0.83 | BH100: 0.5 | BK100: 2.1 | BO100: 0 | BS100: 0 | BW100: 0 | CA100: 1.5 | CE100: 1.4 | CI100: 0 | CM100: 0 | CQ100: 0.55 | CU100: 0 | CY100: 0.1 | DK100: 0 | DO100: 0.83 | DQ100: 0.5 | DS100: 0.83 | DU100: 0.5
A101: =crop!A101 -> Heifer feeding system: 6 months grazing / 6 months maize silage + grass silage (or hay) + soybean meal | Age at first calving: 24 months | B101: =crop!B101 -> A.8.3 | M101: 0.97 | N101: 1.03 | Q101: 0.96 | AA101: 1.82 | AM101: 0.95 | AP101: 0.96 | AX101: 0.68 | BB101: 0.75 | BD101: 0.5 | BF101: 0.75 | BH101: 0.5 | BK101: 1.3 | BO101: 1.5 | BS101: 0 | BW101: 0 | CA101: 0 | CE101: 2.1 | CI101: 0 | CM101: 0 | CQ101: 0.47 | CU101: 0 | CY101: 0.03 | DK101: 0 | DO101: 0.75 | DQ101: 0.5 | DS101: 0.75 | DU101: 0.5
A102: =crop!A102 -> Heifer feeding system: 6 months grazing / 6 months grass silage (or hay) + cereals + soybean meal | Age at first calving: 24 months | B102: =crop!B102 -> A.8.4 | M102: 0.97 | N102: 1.03 | Q102: 0.96 | AA102: 1.82 | AM102: 0.95 | AP102: 0.96 | AX102: 0.68 | BB102: 0.75 | BD102: 0.5 | BF102: 0.75 | BH102: 0.5 | BK102: 0 | BO102: 2.5 | BS102: 0 | BW102: 0 | CA102: 0 | CE102: 2.1 | CI102: 0 | CM102: 0 | CQ102: 0.35 | CU102: 0 | CY102: 0.38 | DK102: 0 | DO102: 0.75 | DQ102: 0.5 | DS102: 0.75 | DU102: 0.5
A103: =crop!A103 -> Heifer feeding system: zero grazing / maize silage + soybean meal | Age at first calving: 29 months | B103: =crop!B103 -> A.8.5 | N103: 0.95 | V103: 0.98 | AI103: 0 | AP103: 1.01 | BD103: 0.5 | BH103: 0.5 | BK103: 4.2 | BO103: 0 | BS103: 0 | BW103: 0 | CA103: 1.2 | CE103: 0 | CI103: 0 | CM103: 0 | CQ103: 0.75 | CU103: 0 | CY103: 0.1 | DK103: 0.5 | DQ103: 0.5 | DU103: 0.5
A104: =crop!A104 -> Heifer feeding system: 4 months grazing / 8 months maize silage + hay + soybean meal | Age at first calving: 29 months | B104: =crop!B104 -> A.8.6 | M104: 0.98 | N104: 0.97 | Q104: 0.98 | V104: 0.98 | AA104: 1.55 | AM104: 0.95 | AP104: 0.99 | AX104: 0.79 | BB104: 0.83 | BD104: 0.5 | BF104: 0.83 | BH104: 0.5 | BK104: 2.7 | BO104: 0 | BS104: 0 | BW104: 0 | CA104: 1.6 | CE104: 1.7 | CI104: 0 | CM104: 0 | CQ104: 0.4 | CU104: 0 | CY104: 0.1 | DK104: 0 | DO104: 0.83 | DQ104: 0.5 | DS104: 0.83 | DU104: 0.5
A105: =crop!A105 -> Heifer feeding system: 6 months grazing / 6 months maize silage + grass silage (or hay) + soybean meal | Age at first calving: 29 months | B105: =crop!B105 -> A.8.7 | M105: 0.97 | N105: 0.98 | Q105: 0.96 | V105: 0.98 | AA105: 1.82 | AM105: 0.95 | AP105: 0.97 | AX105: 0.68 | BB105: 0.75 | BD105: 0.5 | BF105: 0.75 | BH105: 0.5 | BK105: 1.7 | BO105: 1.6 | BS105: 0 | BW105: 0 | CA105: 0 | CE105: 2.6 | CI105: 0 | CM105: 0 | CQ105: 0.25 | CU105: 0 | CY105: 0.1 | DK105: 0 | DO105: 0.75 | DQ105: 0.5 | DS105: 0.75 | DU105: 0.5
A106: =crop!A106 -> Heifer feeding system: 6 months grazing / 6 months grass silage (or hay) + cereals + soybean meal | Age at first calving: 29 months | B106: =crop!B106 -> A.8.8 | M106: 0.97 | N106: 0.98 | Q106: 0.96 | V106: 0.98 | AA106: 1.82 | AM106: 0.95 | AP106: 0.97 | AX106: 0.68 | BB106: 0.75 | BD106: 0.5 | BF106: 0.75 | BH106: 0.5 | BK106: 0 | BO106: 3 | BS106: 0 | BW106: 0 | CA106: 0 | CE106: 2.6 | CI106: 0 | CM106: 0 | CQ106: 0.13 | CU106: 0 | CY106: 0.3 | DK106: 0 | DO106: 0.75 | DQ106: 0.5 | DS106: 0.75 | DU106: 0.5
A107: =crop!A107 -> Systematic antibiotic treatment of cows | B107: =crop!B107 -> A.9.1
A108: =crop!A108 -> Selective antibiotic treatment of cows | B108: =crop!B108 -> A.9.2 | V108: 0.99 | Y108: 1.12 | AD108: 0.77 | AL108: 0.82
A109: =crop!A109 -> Preventive measures of hygiene of the housing conditions (no treatment of cows) | B109: =crop!B109 -> A.9.3 | M109: 1.05 | V109: 0.98 | Y109: 1.16 | Z109: 0.98 | AD109: 0.7 | AL109: 0.77
A110: =crop!A110 -> Systematic anti-parasitic treatment of heifers | B110: =crop!B110 -> A.10.1
A111: =crop!A111 -> Selective/targeted treatment of heifers shedding high amounts of parasites | B111: =crop!B111 -> A.10.2 | AI111: 0.25 | AM111: 0.25
A112: =crop!A112 -> Immunization against internal parasites by low exposure grazing of heifers (no treatment) | B112: =crop!B112 -> A.10.3 | AA112: 0.95 | AI112: 0 | AM112: 0 | BK112: 1.04 | BO112: 1.04 | CA112: 1.03 | CE112: 1.03 | CQ112: 1.03 | CY112: 1.03 | DK112: 1.03
A113: =crop!A113 -> Milk replacer is fed to calves | B113: =crop!B113 -> A.11.1 | M113: 1.05 | N113: 0.95 | O113: 1.05 | P113: 1.05 | Q113: 1.03 | S113: 0.98 | V113: 0.95 | W113: 0.97 | X113: 0.95 | Y113: 1.03 | DB113: 0 | DC113: 1 | DD113: 1 | DE113: 1 | DF113: 0 | DG113: 0 | DH113: 0 | DI113: 0
A114: =crop!A114 -> Milk is fed to calves | B114: =crop!B114 -> A.11.2 | DB114: 0 | DC114: 0 | DD114: 0 | DE114: 0 | DF114: 0 | DG114: 1 | DH114: 1 | DI114: 1
A116: =crop!A116 -> CS #1: maize - wheat - barley | B116: =crop!B116 -> C.12.1.be
A117: =crop!A117 -> CS #1: sugar beet - wheat - potato - wheat | B117: =crop!B117 -> C.12.2.be
A118: =crop!A118 -> CS #1: potato - wheat - rapeseed - wheat | B118: =crop!B118 -> C.12.3.be
A119: =crop!A119 -> CS #1: alfalfa (3 years) - maize - wheat | B119: =crop!B119 -> C.12.4.be
A120: =crop!A120 -> CS #1: potato - wheat - rapeseed - faba bean - wheat | B120: =crop!B120 -> C.12.5.be
A121: =crop!A121 -> CS #1: grassland (3 years) - maize - wheat | B121: =crop!B121 -> C.12.6.be
A122: =crop!A122 -> CS #1: grassland (3 years) - wheat - sugar beet - wheat | B122: =crop!B122 -> C.12.7.be
A123: =crop!A123 -> CS #1: alfalfa (3 years) - maize - wheat - sugar beet - wheat - barley | B123: =crop!B123 -> C.12.8.be
A124: =crop!A124 -> CS #1: grassland (3 years) - maize - wheat - faba bean - wheat - rapeseed - wheat | B124: =crop!B124 -> C.12.9.be
A125: =crop!A125 -> CS #2: maize - wheat - barley | B125: =crop!B125 -> C.13.1.be
A126: =crop!A126 -> CS #2: sugar beet - wheat - potato - wheat | B126: =crop!B126 -> C.13.2.be
A127: =crop!A127 -> CS #2: potato - wheat - rapeseed - wheat | B127: =crop!B127 -> C.13.3.be
... A169: =crop!A169 -> CS #2: grassland (3 years) - maize - wheat - faba bean - rapeseed | B169: =crop!B169 -> C.13.9.pl

Sheet socioeco
C1: Name of the indicator | D1: Fuel consumption wheat (UAA1) | E1: Fuel consumption barley (UAA1) | F1: Fuel consumption sugar beet (UAA1) | G1: Fuel consumption potato (UAA1) | H1: Fuel consumption rapeseed (UAA1) | I1: Fuel consumption pea (UAA1) | J1: Fuel consumption faba bean (UAA1) | K1: Fuel consumption maize (UAA1) | L1: Fuel consumption alfalfa (UAA1) | M1: Fuel consumption sorghum (UAA1) | N1: Fuel consumption TG (UAA1) | O1: Fuel consumption wheat (UAA2) | P1: Fuel consumption barley (UAA2) | Q1: Fuel consumption sugar beet (UAA2) | R1: Fuel consumption potato (UAA2) | S1: Fuel consumption rapeseed (UAA2) | T1: Fuel consumption pea (UAA2) | U1: Fuel consumption faba bean (UAA2) | V1: Fuel consumption maize (UAA2) | W1: Fuel consumption alfalfa (UAA2) | X1: Fuel consumption sorghum (UAA2) | Y1: Fuel consumption TG (UAA2) | Z1: Fuel consumption PG | AA1: Energy demand for machinery | AB1: Energy demand for milking operations | AC1: Work time wheat (UAA1) - Jan | AD1: Work time wheat (UAA1) - Feb | AE1: Work time wheat (UAA1) - March | AF1: Work time wheat (UAA1) - Apr | AG1: Work time wheat (UAA1) - May | AH1: Work time wheat (UAA1) - June | AI1: Work time wheat (UAA1) - July | AJ1: Work time wheat (UAA1) - Aug | AK1: Work time wheat (UAA1) - Sept | AL1: Work time wheat (UAA1) - Oct | AM1: Work time wheat (UAA1) - Nov | AN1: Work time wheat (UAA1) - Dec | AO1: Work time barley (UAA1) - Jan | AP1: Work time barley (UAA1) - Feb | AQ1: Work time barley (UAA1) - March | AR1: Work time barley (UAA1) - Apr | AS1: Work time barley (UAA1) - May | AT1: Work time barley (UAA1) - June | AU1: Work time barley (UAA1) - July | AV1: Work time barley (UAA1) - Aug | AW1: Work time barley (UAA1) - Sept | AX1: Work time barley (UAA1) - Oct | AY1: Work time barley (UAA1) - Nov | AZ1: Work time barley (UAA1) - Dec | BA1: Work time sugar beet (UAA1) - Jan | BB1: Work time sugar beet (UAA1) - Feb | BC1: Work time sugar beet (UAA1) - March | BD1: Work time sugar beet (UAA1) - Apr | BE1: Work time sugar beet (UAA1) - May | BF1: Work time sugar beet (UAA1) - June | BG1: Work time sugar beet (UAA1) - July | BH1: Work time sugar beet (UAA1) - Aug | BI1: Work time sugar beet (UAA1) - Sept | BJ1: Work time sugar beet (UAA1) - Oct | BK1: Work time sugar beet (UAA1) - Nov | BL1: Work time sugar beet (UAA1) - Dec | BM1: Work time potato (UAA1) - Jan | BN1: Work time potato (UAA1) - Feb | BO1: Work time potato (UAA1) - March | BP1: Work time potato (UAA1) - Apr | BQ1: Work time potato (UAA1) - May | BR1: Work time potato (UAA1) - June | BS1: Work time potato (UAA1) - July | BT1: Work time potato (UAA1) - Aug | BU1: Work time potato (UAA1) - Sept | BV1: Work time potato (UAA1) - Oct | BW1: Work time potato (UAA1) - Nov | BX1: Work time potato (UAA1) - Dec | BY1: Work time rapeseed (UAA1) - Jan | BZ1: Work time rapeseed (UAA1) - Feb | CA1: Work time rapeseed (UAA1) - March | CB1: Work time rapeseed (UAA1) - Apr | CC1: Work time rapeseed (UAA1) - May | CD1: Work time rapeseed (UAA1) - June | CE1: Work time rapeseed (UAA1) - July | CF1: Work time rapeseed (UAA1) - Aug | CG1: Work time rapeseed (UAA1) - Sept | CH1: Work time rapeseed (UAA1) - Oct | CI1: Work time rapeseed (UAA1) - Nov | CJ1: Work time rapeseed (UAA1) - Dec | CK1: Work time pea (UAA1) - Jan | CL1: Work time pea (UAA1) - Feb | CM1: Work time pea (UAA1) - March | CN1: Work time pea (UAA1) - Apr | CO1: Work time pea (UAA1) - May | CP1: Work time pea (UAA1) - June | CQ1: Work time pea (UAA1) - July | CR1: Work time pea (UAA1) - Aug | CS1: Work time pea (UAA1) - Sept | CT1: Work time pea (UAA1) - Oct | CU1: Work time pea (UAA1) - Nov | CV1: Work time pea (UAA1) - Dec | CW1: Work time faba bean (UAA1) - Jan | CX1: Work time faba bean (UAA1) - Feb | CY1: Work time faba bean (UAA1) - March | CZ1: Work time faba bean (UAA1) - Apr | DA1: Work time faba bean (UAA1) - May | DB1: Work time faba bean (UAA1) - June | DC1: Work time faba bean (UAA1) - July | DD1: Work time faba bean (UAA1) - Aug | DE1: Work time faba bean (UAA1) - Sept | DF1: Work time faba bean (UAA1) - Oct | DG1: Work time faba bean (UAA1) - Nov | DH1: Work time faba bean (UAA1) - Dec | DI1: Work time maize (UAA1) - Jan | DJ1: Work time maize (UAA1) - Feb | DK1: Work time maize (UAA1) - March | DL1: Work time maize (UAA1) - Apr | DM1: Work time maize (UAA1) - May | DN1: Work time maize (UAA1) - June | DO1: Work time maize (UAA1) - July | DP1: Work time maize (UAA1) - Aug | DQ1: Work time maize (UAA1) - Sept | DR1: Work time maize (UAA1) - Oct | DS1: Work time maize (UAA1) - Nov | DT1: Work time maize (UAA1) - Dec | DU1: Work time alfalfa (UAA1) - Jan | DV1: Work time alfalfa (UAA1) - Feb | DW1: Work time alfalfa (UAA1) - March | DX1: Work time alfalfa (UAA1) - Apr | DY1: Work time alfalfa (UAA1) - May | DZ1: Work time alfalfa (UAA1) - June | EA1: Work time alfalfa (UAA1) - July | EB1: Work time alfalfa (UAA1) - Aug | EC1: Work time alfalfa (UAA1) - Sept | ED1: Work time alfalfa (UAA1) - Oct | EE1: Work time alfalfa (UAA1) - Nov | EF1: Work time alfalfa (UAA1) - Dec | EG1: Work time sorghum (UAA1) - Jan | EH1: Work time sorghum (UAA1) - Feb | EI1: Work time sorghum (UAA1) - March | EJ1: Work time sorghum (UAA1) - Apr | EK1: Work time sorghum (UAA1) - May | EL1: Work time sorghum (UAA1) - June | EM1: Work time sorghum (UAA1) - July | EN1: Work time sorghum (UAA1) - Aug | EO1: Work time sorghum (UAA1) - Sept | EP1: Work time sorghum (UAA1) - Oct | EQ1: Work time sorghum (UAA1) - Nov | ER1: Work time sorghum (UAA1) - Dec | ES1: Work time TG (UAA1) - Jan | ET1: Work time TG (UAA1) - Feb | EU1: Work time TG (UAA1) - March | EV1: Work time TG (UAA1) - Apr | EW1: Work time TG (UAA1) - May | EX1: Work time TG (UAA1) - June | EY1: Work time TG (UAA1) - July | EZ1: Work time TG (UAA1) - Aug | FA1: Work time TG (UAA1) - Sept | FB1: Work time TG (UAA1) - Oct | FC1: Work time TG (UAA1) - Nov | FD1: Work time TG (UAA1) - Dec | FE1: Work time wheat (UAA2) - Jan | FF1: Work time wheat (UAA2) - Feb | FG1: Work time wheat (UAA2) - March | FH1: Work time wheat (UAA2) - Apr | FI1: Work time wheat (UAA2) - May | FJ1: Work time wheat (UAA2) - June | FK1: Work time wheat (UAA2) - July | FL1: Work time wheat (UAA2) - Aug | FM1: Work time wheat (UAA2) - Sept | FN1: Work time wheat (UAA2) - Oct | FO1: Work time wheat (UAA2) - Nov | FP1: Work time wheat (UAA2) - Dec | FQ1: Work time barley (UAA2) - Jan | FR1: Work time barley (UAA2) - Feb | FS1: Work time barley (UAA2) - March | FT1: Work time barley (UAA2) - Apr | FU1: Work time barley (UAA2) - May | FV1: Work time barley (UAA2) - June | FW1: Work time barley (UAA2) - July | FX1: Work time barley (UAA2) - Aug | FY1: Work time barley (UAA2) - Sept | FZ1: Work time barley (UAA2) - Oct | GA1: Work time barley (UAA2) - Nov | GB1: Work time barley (UAA2) - Dec | GC1: Work time sugar beet (UAA2) - Jan | GD1: Work time sugar beet (UAA2) - Feb | GE1: Work time sugar beet (UAA2) - March | GF1: Work time sugar beet (UAA2) - Apr | GG1: Work time sugar beet (UAA2) - May | GH1: Work time sugar beet (UAA2) - June | GI1: Work time sugar beet (UAA2) - July | GJ1: Work time sugar beet (UAA2) - Aug | GK1: Work time sugar beet (UAA2) - Sept | GL1: Work time sugar beet (UAA2) - Oct | GM1: Work time sugar beet (UAA2) - Nov | GN1: Work time sugar beet (UAA2) - Dec | GO1: Work time potato (UAA2) - Jan | GP1: Work time potato (UAA2) - Feb | GQ1: Work time potato (UAA2) - March | GR1: Work time potato (UAA2) - Apr | GS1: Work time potato (UAA2) - May | GT1: Work time potato (UAA2) - June | GU1: Work time potato (UAA2) - July | GV1: Work time potato (UAA2) - Aug | GW1: Work time potato (UAA2) - Sept | GX1: Work time potato (UAA2) - Oct | GY1: Work time potato (UAA2) - Nov | GZ1: Work time potato (UAA2) - Dec | HA1: Work time rapeseed (UAA2) - Jan | HB1: Work time rapeseed (UAA2) - Feb | HC1: Work time rapeseed (UAA2) - March | HD1: Work time rapeseed (UAA2) - Apr | HE1: Work time rapeseed (UAA2) - May | HF1: Work time rapeseed (UAA2) - June | HG1: Work time rapeseed (UAA2) - July | HH1: Work time rapeseed (UAA2) - Aug | HI1: Work time rapeseed (UAA2) - Sept | HJ1: Work time rapeseed (UAA2) - Oct | HK1: Work time rapeseed (UAA2) - Nov | HL1: Work time rapeseed (UAA2) - Dec | HM1: Work time pea (UAA2) - Jan | HN1: Work time pea (UAA2) - Feb | HO1: Work time pea (UAA2) - March | HP1: Work time pea (UAA2) - Apr | HQ1: Work time pea (UAA2) - May | HR1: Work time pea (UAA2) - June | HS1: Work time pea (UAA2) - July | HT1: Work time pea (UAA2) - Aug | HU1: Work time pea (UAA2) - Sept | HV1: Work time pea (UAA2) - Oct | HW1: Work time pea (UAA2) - Nov | HX1: Work time pea (UAA2) - Dec | HY1: Work time faba bean (UAA2) - Jan | HZ1: Work time faba bean (UAA2) - Feb | IA1: Work time faba bean (UAA2) - March | IB1: Work time faba bean (UAA2) - Apr | IC1: Work time faba bean (UAA2) - May | ID1: Work time faba bean (UAA2) - June | IE1: Work time faba bean (UAA2) - July | IF1: Work time faba bean (UAA2) - Aug | IG1: Work time faba bean (UAA2) - Sept | IH1: Work time faba bean (UAA2) - Oct | II1: Work time faba bean (UAA2) - Nov | IJ1: Work time faba bean (UAA2) - Dec | IK1: Work time maize (UAA2) - Jan | IL1: Work time maize (UAA2) - Feb | IM1: Work time maize (UAA2) - March | IN1: Work time maize (UAA2) - Apr | IO1: Work time maize (UAA2) - May | IP1: Work time maize (UAA2) - June | IQ1: Work time maize (UAA2) - July | IR1: Work time maize (UAA2) - Aug | IS1: Work time maize (UAA2) - Sept | IT1: Work time maize (UAA2) - Oct | IU1: Work time maize (UAA2) - Nov | IV1: Work time maize (UAA2) - Dec | IW1: Work time alfalfa (UAA2) - Jan | IX1: Work time alfalfa (UAA2) - Feb | IY1: Work time alfalfa (UAA2) - March | IZ1: Work time alfalfa (UAA2) - Apr | JA1: Work time alfalfa (UAA2) - May | JB1: Work time alfalfa (UAA2) - June | JC1: Work time alfalfa (UAA2) - July | JD1: Work time alfalfa (UAA2) - Aug | JE1: Work time alfalfa (UAA2) - Sept | JF1: Work time alfalfa (UAA2) - Oct | JG1: Work time alfalfa (UAA2) - Nov | JH1: Work time alfalfa (UAA2) - Dec | JI1: Work time sorghum (UAA2) - Jan | JJ1: Work time sorghum (UAA2) - Feb | JK1: Work time sorghum (UAA2) - March | JL1: Work time sorghum (UAA2) - Apr | JM1: Work time sorghum (UAA2) - May | JN1: Work time sorghum (UAA2) - June | JO1: Work time sorghum (UAA2) - July | JP1: Work time sorghum (UAA2) - Aug | JQ1: Work time sorghum (UAA2) - Sept | JR1: Work time sorghum (UAA2) - Oct | JS1: Work time sorghum (UAA2) - Nov | JT1: Work time sorghum (UAA2) - Dec | JU1: Work time TG (UAA2) - Jan | JV1: Work time TG (UAA2) - Feb | JW1: Work time TG (UAA2) - March | JX1: Work time TG (UAA2) - Apr | JY1: Work time TG (UAA2) - May | JZ1: Work time TG (UAA2) - June | KA1: Work time TG (UAA2) - July | KB1: Work time TG (UAA2) - Aug | KC1: Work time TG (UAA2) - Sept | KD1: Work time TG (UAA2) - Oct | KE1: Work time TG (UAA2) - Nov | KF1: Work time TG (UAA2) - Dec | KG1: Work time PG - Jan | KH1: Work time PG - Feb | KI1: Work time PG - March | KJ1: Work time PG - Apr | KK1: Work time PG - May | KL1: Work time PG - June | KM1: Work time PG - July | KN1: Work time PG - Aug | KO1: Work time PG - Sept | KP1: Work time PG - Oct | KQ1: Work time PG - Nov | KR1: Work time PG - Dec | KS1: Various costs for crop production (UAA1) | KT1: Various costs for crop production (UAA2) | KU1: Susbsidies, 1<sup>st</sup> pillar of the CAP | KV1: Susbsidies, 2<sup>nd</sup> pillar of the CAP | KW1: Investment capacity | KX1: Routine work demand for milking | KY1: Routine work demand for feeding (cows) | KZ1: Routine work demand for feeding (other cattle) | LA1: Routine work demand for manure management (cows) | LB1: Routine work demand for manure management (other cattle) | LC1: Routine work demand for heath & care (cows) | LD1: Routine work demand for heath & care (other cattle) | LE1: Routine work demand for other activities (cows) | LF1: Routine work demand for other activities (other cattle) | LG1: Investment in buildings and agroforestry | LH1: Organic farming | LI1: Complexity of the system
A2: AEP name | B2: AEP_ID | C2: IndicatorID | D2: =INDEX([1]indicators!$I$2:$I$1491,MATCH(D$1,[1]indicators!$C$2:$C$1491,0),1) -> indCr77.UAA1 | E2: =INDEX([1]indicators!$I$2:$I$1491,MATCH(E$1,[1]indicators!$C$2:$C$1491,0),1) -> indCr78.UAA1 | F2: =INDEX([1]indicators!$I$2:$I$1491,MATCH(F$1,[1]indicators!$C$2:$C$1491,0),1) -> indCr79.UAA1 | G2: =INDEX([1]indicators!$I$2:$I$1491,MATCH(G$1,[1]indicators!$C$2:$C$1491,0),1) -> indCr80.UAA1 | H2: =INDEX([1]indicators!$I$2:$I$1491,MATCH(H$1,[1]indicators!$C$2:$C$1491,0),1) -> indCr81.UAA1 | I2: =INDEX([1]indicators!$I$2:$I$1491,MATCH(I$1,[1]indicators!$C$2:$C$1491,0),1) -> indCr82.UAA1 | J2: =INDEX([1]indicators!$I$2:$I$1491,MATCH(J$1,[1]indicators!$C$2:$C$1491,0),1) -> indCr83.UAA1 | K2: =INDEX([1]indicators!$I$2:$I$1491,MATCH(K$1,[1]indicators!$C$2:$C$1491,0),1) -> indCr84.UAA1 | ... LI2: =INDEX([1]indicators!$I$2:$I$1491,MATCH(LI$1,[1]indicators!$C$2:$C$1491,0),1) -> indGl2
A3: =crop!A3 -> Conventional tillage (CT) | B3: =crop!B3 -> C.1.1 | D3: =4.96+24.9+13.97 -> 43.83 | E3: =4.96+24.9+13.97 -> 43.83 | F3: =4.96*3+24.9+9.02 -> 48.8 | G3: =79+24 -> 103 | H3: =4.96*2+24.9+13.97 -> 48.79 | I3: =4.96+24.9+13.97 -> 43.83 | J3: =4.96+24.9+13.97 -> 43.83 | K3: =4.96*3+24.9+9.02 -> 48.8 | L3: =K3/2.5 -> 19.52 | M3: =K3 -> 48.8 | N3: =(4.96*2+24.9+9.02)/3 -> 14.613333 | O3: =4.96+24.9+13.97 -> 43.83 | P3: =4.96+24.9+13.97 -> 43.83 | Q3: =4.96*3+24.9+9.02 -> 48.8 | R3: =79+24 -> 103 | S3: =4.96*2+24.9+13.97 -> 48.79 | T3: =4.96+24.9+13.97 -> 43.83 | U3: =4.96+24.9+13.97 -> 43.83 | V3: =4.96*3+24.9+9.02 -> 48.8 | W3: =V3/2.5 -> 19.52 | X3: =V3 -> 48.8 | Y3: =(4.96*2+24.9+9.02)/3 -> 14.613333 | AL3: =0.31+1.33+0.83 -> 2.47 | AX3: =0.31+1.33+0.83 -> 2.47 | BC3: =0.31+0.67 -> 0.98 | BI3: =0.31*2+1.33 -> 1.95 | BP3: =0.31*3+1.33+2+2 -> 6.26 | BU3: =2*0.31 -> 0.62 | CE3: =0.31*2 -> 0.62 | CF3: =1.33+0.83 -> 2.16 | CT3: =0.31+1.33+0.83 -> 2.47 | DG3: =0.31+1.33+0.83 -> 2.47 | DL3: =0.31*2+1.33+0.67 -> 2.62 | DQ3: 0.31 | EB3: =(0.31*3+1.33+0.67)/2.5 -> 1.172 | EK3: =0.31*2+1.33+0.67 -> 2.62 | EO3: 0.31 | EZ3: =(0.31*2+1.33+0.67)/3 -> 0.87333333 | FN3: =0.31+1.33+0.83 -> 2.47 | FZ3: =0.31+1.33+0.83 -> 2.47 | GE3: =0.31+0.67 -> 0.98 | GK3: =0.31*2+1.33 -> 1.95 | GR3: =0.31*3+1.33+2+2 -> 6.26 | GW3: =2*0.31 -> 0.62 | HG3: =0.31*2 -> 0.62 | HH3: =1.33+0.83 -> 2.16 | HV3: =0.31+1.33+0.83 -> 2.47 | II3: =0.31+1.33+0.83 -> 2.47 | IN3: =0.31*2+1.33+0.67 -> 2.62 | IS3: 0.31 | JD3: =(0.31*3+1.33+0.67)/2.5 -> 1.172 | JM3: =0.31*2+1.33+0.67 -> 2.62 | JQ3: 0.31 | KB3: =(0.31*2+1.33+0.67)/3 -> 0.87333333
A4: =crop!A4 -> Reduced tillage (RT) | B4: =crop!B4 -> C.1.2 | D4: =4.96+13.97 -> 18.93 | E4: =4.96+13.97 -> 18.93 | F4: =4.96*3+9.02 -> 23.9 | G4: =79-24.9+24 -> 78.1 | H4: =4.96*2+13.97 -> 23.89 | I4: =4.96*3+13.97 -> 28.85 | J4: =4.96*3+13.97 -> 28.85 | K4: =4.96*3+9.02 -> 23.9 | L4: =K4/2.5 -> 9.56 | M4: =K4 -> 23.9 | N4: =(4.96*2+9.02)/3 -> 6.3133333 | O4: =4.96+13.97 -> 18.93 | P4: =4.96+13.97 -> 18.93 | Q4: =4.96*3+9.02 -> 23.9 | R4: =79-24.9+24 -> 78.1 | S4: =4.96*2+13.97 -> 23.89 | T4: =4.96*3+13.97 -> 28.85 | U4: =4.96*3+13.97 -> 28.85 | V4: =4.96*3+9.02 -> 23.9 | W4: =V4/2.5 -> 9.56 | X4: =V4 -> 23.9 | Y4: =(4.96*2+9.02)/3 -> 6.3133333 | AL4: =0.31+0.83 -> 1.14 | AX4: =0.31+0.83 -> 1.14 | BC4: =0.31+0.67 -> 0.98 | BI4: =0.31*2 -> 0.62 | BP4: =0.31*3+2+2 -> 4.93 | BU4: =2*0.31 -> 0.62 | CE4: =2*0.31 -> 0.62 | CF4: 0.83 | CT4: =0.31*3+0.83 -> 1.76 | DG4: =0.31*3+0.83 -> 1.76 | DL4: =0.31*2+0.67 -> 1.29 | DQ4: 0.31 | EB4: =(0.31*3+0.67)/2.5 -> 0.64 | EK4: =0.31*2+0.67 -> 1.29 | EO4: 0.31 | EZ4: =(0.31*2+0.67)/3 -> 0.43 | FN4: =0.31+0.83 -> 1.14 | FZ4: =0.31+0.83 -> 1.14 | GE4: =0.31+0.67 -> 0.98 | GK4: =0.31*2 -> 0.62 | GR4: =0.31*3+2+2 -> 4.93 | GW4: =2*0.31 -> 0.62 | HG4: =2*0.31 -> 0.62 | HH4: 0.83 | HV4: =0.31*3+0.83 -> 1.76 | II4: =0.31*3+0.83 -> 1.76 | IN4: =0.31*2+0.67 -> 1.29 | IS4: 0.31 | JD4: =(0.31*3+0.67)/2.5 -> 0.64 | JM4: =0.31*2+0.67 -> 1.29 | JQ4: 0.31 | KB4: =(0.31*2+0.67)/3 -> 0.43 | KS4: 0.9 | KT4: 0.9 | LI4: -0.25
A5: =crop!A5 -> No tillage (NT) | B5: =crop!B5 -> C.1.3 | D5: 6 | E5: 6 | F5: 6 | G5: =24.3+7.1 -> 31.4 | H5: 6 | I5: 6 | J5: 6 | K5: 6 | L5: =K5/2.5 -> 2.4 | M5: 6 | N5: =K5/3 -> 2 | O5: 6 | P5: 6 | Q5: 6 | R5: =24.3+7.1 -> 31.4 | S5: 6 | T5: 6 | U5: 6 | V5: 6 | W5: =V5/2.5 -> 2.4 | X5: 6 | Y5: =V5/3 -> 2 | AL5: 0.42 | AX5: 0.42 | BC5: 0.42 | BP5: =2+2 -> 4 | CF5: 0.42 | CT5: 0.42 | DG5: 0.42 | DL5: 0.42 | EB5: =0.42/2.5 -> 0.168 | EK5: 0.42 | EZ5: =0.42/3 -> 0.14 | FN5: 0.42 | FZ5: 0.42 | GE5: 0.42 | GR5: =2+2 -> 4 | HH5: 0.42 | HV5: 0.42 | II5: 0.42 | IN5: 0.42 | JD5: =0.42/2.5 -> 0.168 | JM5: 0.42 | KB5: =0.42/3 -> 0.14 | KS5: 0.8 | KT5: 0.8 | LI5: -0.5
A6: =crop!A6 -> Fall cover crop destructed before winter | B6: =crop!B6 -> C.2.1 | D6: 6 | E6: 6 | F6: 6 | G6: 6 | H6: 6 | I6: 6 | J6: 6 | K6: 6 | M6: 6 | O6: 6 | P6: 6 | Q6: 6 | R6: 6 | S6: 6 | T6: 6 | U6: 6 | V6: 6 | X6: 6 | AJ6: 0.42 | AV6: 0.42 | BK6: 0.42 | BU6: 0.42 | CF6: 0.42 | CR6: 0.42 | DD6: 0.42 | DR6: 0.42 | EP6: 0.42 | FL6: 0.42 | FX6: 0.42 | GM6: 0.42 | GW6: 0.42 | HH6: 0.42 | HT6: 0.42 | IF6: 0.42 | IT6: 0.42 | JR6: 0.42 | KS6: 1.2 | KT6: 1.2
A7: =crop!A7 -> Fall cover crop destructed early spring | B7: =crop!B7 -> C.2.2 | D7: 6 | E7: 6 | F7: 6 | G7: 6 | H7: 6 | I7: 6 | J7: 6 | K7: 6 | M7: 6 | O7: 6 | P7: 6 | Q7: 6 | R7: 6 | S7: 6 | T7: 6 | U7: 6 | V7: 6 | X7: 6 | AJ7: 0.42 | AV7: 0.42 | BK7: 0.42 | BU7: 0.42 | CF7: 0.42 | CR7: 0.42 | DD7: 0.42 | DR7: 0.42 | EP7: 0.42 | FL7: 0.42 | FX7: 0.42 | GM7: 0.42 | GW7: 0.42 | HH7: 0.42 | HT7: 0.42 | IF7: 0.42 | IT7: 0.42 | JR7: 0.42 | KS7: 1.2 | KT7: 1.2
A8: =crop!A8 -> Permanent soil cover | B8: =crop!B8 -> C.2.3 | D8: =6/3 -> 2 | E8: =6/3 -> 2 | F8: =6/3 -> 2 | G8: =6/3 -> 2 | H8: =6/3 -> 2 | I8: =6/3 -> 2 | J8: 2 | K8: =6/3 -> 2 | M8: =6/3 -> 2 | O8: =6/3 -> 2 | P8: =6/3 -> 2 | Q8: =6/3 -> 2 | R8: =6/3 -> 2 | S8: =6/3 -> 2 | T8: =6/3 -> 2 | U8: 2 | V8: =6/3 -> 2 | X8: =6/3 -> 2 | AJ8: =0.42/3 -> 0.14 | AV8: =0.42/3 -> 0.14 | BK8: =0.42/3 -> 0.14 | BU8: =0.42/3 -> 0.14 | CF8: =0.42/3 -> 0.14 | CR8: =0.42/3 -> 0.14 | DD8: =0.42/3 -> 0.14 | DR8: =0.42/3 -> 0.14 | EP8: =0.42/3 -> 0.14 | FL8: =0.42/3 -> 0.14 | FX8: =0.42/3 -> 0.14 | GM8: =0.42/3 -> 0.14 | GW8: =0.42/3 -> 0.14 | HH8: =0.42/3 -> 0.14 | HT8: =0.42/3 -> 0.14 | IF8: =0.42/3 -> 0.14 | IT8: =0.42/3 -> 0.14 | JR8: =0.42/3 -> 0.14 | KS8: 0.8 | KT8: 0.8 | LI8: -0.5
A9: =crop!A9 -> Straw removal | B9: =crop!B9 -> C.3.1 | D9: =11.7+8.94 -> 20.64 | E9: =11.7+8.94 -> 20.64 | I9: =-20.64 -> -20.64 | O9: =11.7+8.94 -> 20.64 | P9: =11.7+8.94 -> 20.64 | T9: =-20.64 -> -20.64 | AI9: =0.5+0.67 -> 1.17 | AU9: =0.5+0.67 -> 1.17 | CQ9: =-(0.5+0.67) -> -1.17 | FK9: =0.5+0.67 -> 1.17 | FW9: =0.5+0.67 -> 1.17 | HS9: =-(0.5+0.67) -> -1.17 | KS9: 1.05 | KT9: 1.05
A10: =crop!A10 -> Straw left on soil | B10: =crop!B10 -> C.3.2 | D10: =9.02 -> 9.02 | E10: =9.02 -> 9.02 | I10: =-9.02 -> -9.02 | O10: =9.02 -> 9.02 | P10: =9.02 -> 9.02 | T10: =-9.02 -> -9.02 | AI10: 0.67 | AU10: 0.67 | CQ10: -0.67 | FK10: 0.67 | FW10: 0.67 | HS10: -0.67 | KS10: 0.9 | KT10: 0.9
A11: =crop!A11 -> On-farm organic fertilizers + input of mineral fertilizer | B11: =crop!B11 -> C.4.1 | D11: =2*1.56 -> 3.12 | E11: =2*1.56 -> 3.12 | F11: =2*1.56 -> 3.12 | G11: =2*1.56 -> 3.12 | H11: 1.56 | I11: =-2*1.56 -> -3.12 | K11: =1.56*1 -> 1.56 | M11: =1.56*1 -> 1.56 | O11: =2*1.56 -> 3.12 | P11: =2*1.56 -> 3.12 | Q11: =2*1.56 -> 3.12 | R11: =2*1.56 -> 3.12 | S11: 1.56 | T11: =-2*1.56 -> -3.12 | V11: =1.56*1 -> 1.56 | X11: =1.56*1 -> 1.56 | AF11: 0.12 | AG11: 0.12 | AR11: 0.12 | AS11: 0.12 | BC11: 0.12 | BI11: 0.12 | BP11: 0.12 | BQ11: 0.12 | BZ11: 0.12 | CN11: -0.12 | CO11: -0.12 | DM11: 0.12 | EK11: 0.12 | FH11: 0.12 | FI11: 0.12 | FT11: 0.12 | FU11: 0.12 | GE11: 0.12 | GK11: 0.12 | GR11: 0.12 | GS11: 0.12 | HB11: 0.12 | HP11: -0.12 | HQ11: -0.12 | IO11: 0.12 | JM11: 0.12 | KS11: 1.05 | KT11: 1.05
A12: =crop!A12 -> On-farm organic fertilizers only | B12: =crop!B12 -> C.4.2
A13: =crop!A13 -> Systematic use of chemical fungicides | B13: =crop!B13 -> C.5.1 | AE13: 0.11 | AF13: 0.11 | AG13: 0.11 | AR13: 0.11 | BG13: 0.11 | BH13: =0.11*2 -> 0.22 | BQ13: =2*0.11 -> 0.22 | BR13: =4*0.11 -> 0.44 | BS13: =4*0.11 -> 0.44 | BT13: =4*0.11 -> 0.44 | CB13: 0.11 | CM13: 0.11 | CN13: 0.11 | CO13: -0.11 | CZ13: 0.11 | FG13: 0.11 | FH13: 0.11 | FI13: 0.11 | FT13: 0.11 | GI13: 0.11 | GJ13: =0.11*2 -> 0.22 | GS13: =2*0.11 -> 0.22 | GT13: =4*0.11 -> 0.44 | GU13: =4*0.11 -> 0.44 | GV13: =4*0.11 -> 0.44 | HD13: 0.11 | HO13: 0.11 | HP13: 0.11 | HQ13: -0.11 | IB13: 0.11
A14: =crop!A14 -> Sound approach of chemical fungicides | B14: =crop!B14 -> C.5.2 | AE14: 0.11 | AF14: 0.11 | BG14: 0.11 | BH14: 0.11 | BQ14: 0.11 | BR14: =3*0.11 -> 0.33 | BS14: =3*0.11 -> 0.33 | BT14: =3*0.11 -> 0.33 | CM14: 0.11 | CN14: -0.11 | FG14: 0.11 | FH14: 0.11 | GI14: 0.11 | GJ14: 0.11 | GS14: 0.11 | GT14: =3*0.11 -> 0.33 | GU14: =3*0.11 -> 0.33 | GV14: =3*0.11 -> 0.33 | HO14: 0.11 | HP14: -0.11 | KS14: 0.9 | KT14: 0.9 | LI14: -0.5
A15: =crop!A15 -> Biocontrol products against diseases | B15: =crop!B15 -> C.5.3 | BH15: 0.11 | BQ15: =2*0.11 -> 0.22 | BR15: =4*0.11 -> 0.44 | BS15: =4*0.11 -> 0.44 | BT15: =4*0.11 -> 0.44 | GJ15: 0.11 | GS15: =2*0.11 -> 0.22 | GT15: =4*0.11 -> 0.44 | GU15: =4*0.11 -> 0.44 | GV15: =4*0.11 -> 0.44 | KS15: 0.85 | KT15: 0.85 | KV15: 1 | LI15: -0.5
A16: =crop!A16 -> No direct protection against diseases | B16: =crop!B16 -> C.5.4 | KS16: 0.8 | KT16: 0.8 | KV16: 1
A17: =crop!A17 -> Systematic and sole use of chemical herbicides | B17: =crop!B17 -> C.6.1 | AE17: 0.11 | AM17: 0.11 | AY17: 0.11 | BC17: 0.11 | BD17: 0.11 | BE17: 0.11 | BP17: 0.11 | BT17: =2*0.11 -> 0.22 | CA17: 0.11 | CF17: 0.11 | CU17: 0.11 | DG17: 0.11 | DL17: 0.11 | DM17: 0.11 | EC17: =0.11/2.5 -> 0.044 | EK17: 0.11 | EZ17: 0.11 | FG17: 0.11 | FO17: 0.11 | GA17: 0.11 | GE17: 0.11 | GF17: 0.11 | GG17: 0.11 | GR17: 0.11 | GV17: =2*0.11 -> 0.22 | HC17: 0.11 | HH17: 0.11 | HW17: 0.11 | II17: 0.11 | IN17: 0.11 | IO17: 0.11 | JE17: =0.11/2.5 -> 0.044 | JM17: 0.11 | KB17: 0.11
A18: =crop!A18 -> Sound approach of chemical herbicides + mechanical weed control | B18: =crop!B18 -> C.6.2 | D18: 4.95 | E18: 4.95 | F18: =2*4.95 -> 9.9 | G18: 9.02 | H18: 4.95 | I18: 4.95 | J18: =4.95*2 -> 9.9 | K18: 4.95 | L18: =K18/2.5 -> 1.98 | M18: 4.95 | N18: =K18/3 -> 1.65 | O18: 4.95 | P18: 4.95 | Q18: =2*4.95 -> 9.9 | R18: 9.02 | S18: 4.95 | T18: 4.95 | U18: =4.95*2 -> 9.9 | V18: 4.95 | W18: =V18/2.5 -> 1.98 | X18: 4.95 | Y18: =V18/3 -> 1.65 | AE18: 0.11 | AM18: 0.33 | AQ18: 0.11 | AY18: 0.33 | BC18: 0.11 | BD18: =0.11+0.33 -> 0.44 | BE18: 0.33 | BP18: 0.11 | BT18: 0.67 | CA18: 0.11 | CF18: 0.33 | CM18: 0.11 | CU18: 0.33 | CY18: 0.33 | DG18: 0.33 | DM18: =0.33+0.11 -> 0.44 | EC18: =0.33/2.5 -> 0.132 | EK18: 0.33 | FG18: 0.11 | FO18: 0.33 | FS18: 0.11 | GA18: 0.33 | GE18: 0.11 | GF18: =0.11+0.33 -> 0.44 | GG18: 0.33 | GR18: 0.11 | GV18: 0.67 | HC18: 0.11 | HH18: 0.33 | HO18: 0.11 | HW18: 0.33 | IA18: 0.33 | II18: 0.33 | IO18: =0.33+0.11 -> 0.44 | JE18: =0.33/2.5 -> 0.132 | JM18: 0.33 | KS18: 0.9 | KT18: 0.9 | KV18: 1 | LI18: -0.25
A19: =crop!A19 -> Sole use of mechanical weed control | B19: =crop!B19 -> C.6.3 | D19: =4.95*2 -> 9.9 | E19: =4.95*2 -> 9.9 | F19: =3*4.95 -> 14.85 | G19: =4.95+9.02 -> 13.97 | H19: =4.95*2 -> 9.9 | I19: =4.95*2 -> 9.9 | J19: =4.95*2 -> 9.9 | K19: =4.95*2 -> 9.9 | L19: =K19/2/2.5 -> 1.98 | M19: 4.95 | N19: =K19/2/3 -> 1.65 | O19: =4.95*2 -> 9.9 | P19: =4.95*2 -> 9.9 | Q19: =3*4.95 -> 14.85 | R19: =4.95+9.02 -> 13.97 | S19: =4.95*2 -> 9.9 | T19: =4.95*2 -> 9.9 | U19: =4.95*2 -> 9.9 | V19: =4.95*2 -> 9.9 | W19: =V19/2/2.5 -> 1.98 | X19: 4.95 | Y19: =V19/2/3 -> 1.65 | AE19: 0.33 | AM19: 0.33 | AQ19: 0.33 | AY19: 0.33 | BC19: 0.33 | BD19: 0.33 | BE19: 0.33 | BQ19: 0.33 | BT19: 0.67 | CA19: 0.33 | CF19: 0.33 | CM19: 0.33 | CU19: 0.33 | CY19: 0.33 | DG19: 0.33 | DL19: 0.33 | DM19: 0.33 | EC19: =0.33/2.5 -> 0.132 | EK19: 0.33 | FG19: 0.33 | FO19: 0.33 | FS19: 0.33 | GA19: 0.33 | GE19: 0.33 | GF19: 0.33 | GG19: 0.33 | GS19: 0.33 | GV19: 0.67 | HC19: 0.33 | HH19: 0.33 | HO19: 0.33 | HW19: 0.33 | IA19: 0.33 | II19: 0.33 | IN19: 0.33 | IO19: 0.33 | JE19: =0.33/2.5 -> 0.132 | JM19: 0.33 | KS19: 1.1 | KT19: 1.1 | KV19: 1 | LI19: -0.5
A20: =crop!A20 -> Systematic use of chemical insecticides / molluscicides / nematicides | B20: =crop!B20 -> C.7.1 | AG20: 0.11 | BE20: 0.11 | BG20: 0.11 | BQ20: 0.11 | BR20: 0.11 | BS20: 0.11 | CA20: 0.11 | CB20: 0.11 | CG20: 0.11 | CO20: 0.11 | DA20: 0.11 | DN20: 0.11 | EB20: =0.11/2.5 -> 0.044 | FI20: 0.11 | GG20: 0.11 | GI20: 0.11 | GS20: 0.11 | GT20: 0.11 | GU20: 0.11 | HC20: 0.11 | HD20: 0.11 | HI20: 0.11 | HQ20: 0.11 | IC20: 0.11 | IP20: 0.11 | JD20: =0.11/2.5 -> 0.044
A21: =crop!A21 -> Sound approach of chemical insecticides / molluscicides / nematicides | B21: =crop!B21 -> C.7.2 | BG21: 0.11 | BQ21: 0.11 | BR21: 0.11 | CA21: 0.11 | CB21: 0.11 | GI21: 0.11 | GS21: 0.11 | GT21: 0.11 | HC21: 0.11 | HD21: 0.11 | KS21: 0.9 | KT21: 0.9 | LI21: -0.5
A22: =crop!A22 -> Biocontrol products (incl. pyrethrin) and other natural control techniques against pests | B22: =crop!B22 -> C.7.3 | BG22: 0.11 | BR22: 0.11 | DN22: 0.22 | GI22: 0.11 | GT22: 0.11 | IP22: 0.22 | KS22: 0.85 | KT22: 0.85 | KV22: 1 | LI22: -0.5
A23: =crop!A23 -> No direct protection against animal pests | B23: =crop!B23 -> C.7.4 | KS23: 0.8 | KT23: 0.8 | KV23: 1
A24: =crop!A24 -> High yielding cultivars | B24: =crop!B24 -> C.8.1
A25: =crop!A25 -> Resistant cultivars and/or mix of varieties | B25: =crop!B25 -> C.8.2 | KS25: 0.9 | KT25: 0.9 | LI25: -0.25
A26: =crop!A26 -> Temporary grassland composed of grass | B26: =crop!B26 -> C.9.1
A27: =crop!A27 -> Temporary grassland composed of simple grass/legume mixtures | B27: =crop!B27 -> C.9.2
A28: =crop!A28 -> Temporary grassland composed of complex grass/legume mixtures | B28: =crop!B28 -> C.9.3 | LI28: -0.25
A29: =crop!A29 -> No permanent grassland | B29: =crop!B29 -> C.10.1
A30: =crop!A30 -> Permanent grassland occupy a small percentage of the farm area | B30: =crop!B30 -> C.10.2
A31: =crop!A31 -> Permanent grassland occupy a high percentage of the farm area | B31: =crop!B31 -> C.10.3 | KV31: 1
A32: =crop!A32 -> Sole crops | B32: =crop!B32 -> C.11.1
A33: =crop!A33 -> Wheat/pea intercrops | B33: =crop!B33 -> C.11.2 | LI33: -0.25
A34: =crop!A34 -> CS #1: maize - wheat | B34: =crop!B34 -> C.12.1 | KU34: 0.8
A35: =crop!A35 -> CS #1: rapeseed - wheat - maize - wheat | B35: =crop!B35 -> C.12.2 | LI35: -0.125
A36: =crop!A36 -> CS #1: maize - wheat - maize - barley | B36: =crop!B36 -> C.12.3 | LI36: -0.125
A37: =crop!A37 -> CS #1: alfalfa (3 years) - maize - wheat | B37: =crop!B37 -> C.12.4 | KS37: 1.1 | LI37: -0.125
A38: =crop!A38 -> CS #1: faba bean - wheat - rapeseed - maize | B38: =crop!B38 -> C.12.5 | KS38: 1.1 | LI38: -0.125
A39: =crop!A39 -> CS #1: grassland (4 years) - maize - maize | B39: =crop!B39 -> C.12.6 | KS39: 0.7 | LI39: -0.125
A40: =crop!A40 -> CS #1: grassland (3 years) - maize - wheat - barley | B40: =crop!B40 -> C.12.7 | KS40: 0.7 | LI40: -0.125
A41: =crop!A41 -> CS #1: faba bean - wheat - maize - alfalfa (3 years) - barley - maize | B41: =crop!B41 -> C.12.8 | KS41: 0.8 | KV41: 1 | LI41: -0.25
A42: =crop!A42 -> CS #1: grassland (3 years) - maize - wheat - faba bean - rapeseed | B42: =crop!B42 -> C.12.9 | KS42: 0.8 | KV42: 1 | LI42: -0.25
A43: =crop!A43 -> CS #2: maize - wheat | B43: =crop!B43 -> C.13.1 | KU43: 0.8
A44: =crop!A44 -> CS #2: rapeseed - wheat - maize - wheat | B44: =crop!B44 -> C.13.2 | LI44: -0.125
A45: =crop!A45 -> CS #2: maize - wheat - maize - barley | B45: =crop!B45 -> C.13.3 | LI45: -0.125
A46: =crop!A46 -> CS #2: alfalfa (3 years) - maize - wheat | B46: =crop!B46 -> C.13.4 | KT46: 1.1 | LI46: -0.125
A47: =crop!A47 -> CS #2: faba bean - wheat - rapeseed - maize | B47: =crop!B47 -> C.13.5 | KT47: 1.1 | LI47: -0.125
A48: =crop!A48 -> CS #2: grassland (4 years) - maize - maize | B48: =crop!B48 -> C.13.6 | KT48: 0.7 | LI48: -0.125
A49: =crop!A49 -> CS #2: grassland (3 years) - maize - wheat - barley | B49: =crop!B49 -> C.13.7 | KT49: 0.7 | LI49: -0.125
A50: =crop!A50 -> CS #2: faba bean - wheat - maize - alfalfa (3 years) - barley - maize | B50: =crop!B50 -> C.13.8 | KT50: 0.8 | KV50: 1 | LI50: -0.25
A51: =crop!A51 -> CS #2: grassland (3 years) - maize - wheat - faba bean - rapeseed | B51: =crop!B51 -> C.13.9 | KT51: 0.8 | KV51: 1 | LI51: -0.25
A52: =crop!A52 -> No particular green infrastructure elements | B52: =crop!B52 -> C.14.1 | KU52: 0.8
A53: =crop!A53 -> Sown field margins as green infrastructures: wildflowers strip | B53: =crop!B53 -> C.14.2
A54: =crop!A54 -> Sown field margins as green infrastructures: beetle bank (for birds and polyphagous predator) | B54: =crop!B54 -> C.14.3 | LI54: -0.125
A55: =crop!A55 -> Semi-natural field margins as green infrastructures: hedgerows | B55: =crop!B55 -> C.14.4 | LI55: -0.125
A56: =crop!A56 -> Semi-natural field margins as green infrastructures: grass margins | B56: =crop!B56 -> C.14.5
A57: =crop!A57 -> No agroforestry | B57: =crop!B57 -> C.15.1
A58: =crop!A58 -> In-field agroforestry | B58: =crop!B58 -> C.15.2 | LI58: -0.5
A59: =crop!A59 -> Balanced strategy between farmer income and investment | B59: =crop!B59 -> E.1.1 | KW59: 0.5
A60: =crop!A60 -> Investment-oriented strategy | B60: =crop!B60 -> E.1.2 | KW60: 0.8
A61: =crop!A61 -> Income-oriented strategy | B61: =crop!B61 -> E.1.3 | KW61: 0.2
A62: =crop!A62 -> Conventional farming | B62: =crop!B62 -> G.1.1
A63: =crop!A63 -> Organic farming | B63: =crop!B63 -> G.1.2 | LH63: 1
A64: =crop!A64 -> Cattle breed is Holstein | B64: =crop!B64 -> A.1.1
A65: =crop!A65 -> Cattle breed is Siemmental | B65: =crop!B65 -> A.1.2
A66: =crop!A66 -> Cattle breed is Montbéliarde | B66: =crop!B66 -> A.1.3
A67: =crop!A67 -> Initial herd size | B67: =crop!B67 -> A.2.1
A68: =crop!A68 -> 15% increase of initial herd size (no building modification) | B68: =crop!B68 -> A.2.2 | KX68: 1.05 | LC68: 1.05 | LI68: -0.25
A69: =crop!A69 -> 15% increase of initial herd size (building modification) | B69: =crop!B69 -> A.2.3 | KX69: 1.05 | LI69: -0.25
A70: =crop!A70 -> 30% increase of initial herd size (building modification) | B70: =crop!B70 -> A.2.4 | KX70: 0.76923077 | LI70: -0.25
A71: =crop!A71 -> 15% decrease of initial herd size | B71: =crop!B71 -> A.2.5
A72: =crop!A72 -> 30% decrease of initial herd size | B72: =crop!B72 -> A.2.6
A73: =crop!A73 -> Bulls fattened up to 18 months | B73: =crop!B73 -> A.3.1 | LI73: -0.5
A74: =crop!A74 -> Castrated males fattened up to 36 months (steer) | B74: =crop!B74 -> A.3.2 | KZ74: 0.9 | LB74: 0.9 | LD74: 0.9 | LF74: 0.9 | LI74: -0.5
A75: =crop!A75 -> Male calves sold at 8 days | B75: =crop!B75 -> A.3.3
A76: =crop!A76 -> Cows are tied on straw bedding | B76: =crop!B76 -> A.4.1 | D76: 11.57 | E76: 11.57 | F76: 11.57 | G76: 11.57 | H76: 11.57 | I76: -11.57 | K76: 11.57 | M76: 11.57 | N76: 11.57 | O76: 11.57 | P76: 11.57 | Q76: 11.57 | R76: 11.57 | S76: 11.57 | T76: -11.57 | V76: 11.57 | X76: 11.57 | Y76: 11.57 | Z76: 11.57 | AA76: 2.5 | AB76: 0.075 | AD76: =1.33/2 -> 0.665 | AP76: =1.33/2 -> 0.665 | BI76: =1.33/2 -> 0.665 | BU76: =1.33/2 -> 0.665 | CG76: =1.33/2 -> 0.665 | CL76: =-1.33/2 -> -0.665 | DJ76: =1.33/2 -> 0.665 | EI76: =1.33/2 -> 0.665 | EZ76: =1.33/2 -> 0.665 | FF76: =1.33/2 -> 0.665 | FR76: =1.33/2 -> 0.665 | GK76: =1.33/2 -> 0.665 | GW76: =1.33/2 -> 0.665 | HI76: =1.33/2 -> 0.665 | HN76: =-1.33/2 -> -0.665 | IL76: =1.33/2 -> 0.665 | JK76: =1.33/2 -> 0.665 | KB76: =1.33/2 -> 0.665 | KN76: =1.33/2 -> 0.665 | LA76: 2 | LE76: 1.2
A77: =crop!A77 -> Housing of cows is cubicles with straw (shallow bedding) | B77: =crop!B77 -> A.4.2 | D77: 11.57 | E77: 11.57 | F77: 11.57 | G77: 11.57 | H77: 11.57 | I77: -11.57 | K77: 11.57 | M77: 11.57 | N77: 11.57 | O77: 11.57 | P77: 11.57 | Q77: 11.57 | R77: 11.57 | S77: 11.57 | T77: -11.57 | V77: 11.57 | X77: 11.57 | Y77: 11.57 | Z77: 11.57 | AA77: 2.5 | AB77: 0.066 | AD77: =1.33/2 -> 0.665 | AP77: =1.33/2 -> 0.665 | BI77: =1.33/2 -> 0.665 | BU77: =1.33/2 -> 0.665 | CG77: =1.33/2 -> 0.665 | CL77: =-1.33/2 -> -0.665 | DJ77: =1.33/2 -> 0.665 | EI77: =1.33/2 -> 0.665 | EZ77: =1.33/2 -> 0.665 | FF77: =1.33/2 -> 0.665 | FR77: =1.33/2 -> 0.665 | GK77: =1.33/2 -> 0.665 | GW77: =1.33/2 -> 0.665 | HI77: =1.33/2 -> 0.665 | HN77: =-1.33/2 -> -0.665 | IL77: =1.33/2 -> 0.665 | JK77: =1.33/2 -> 0.665 | KB77: =1.33/2 -> 0.665 | KN77: =1.33/2 -> 0.665 | LA77: 1.2 | LG77: 165600
A78: =crop!A78 -> Housing of cows is cubicles with slatted floor | B78: =crop!B78 -> A.4.3 | D78: 5 | E78: 5 | F78: 5 | G78: 5 | H78: 5 | I78: -5 | K78: 5 | M78: 5 | N78: 5 | O78: 5 | P78: 5 | Q78: 5 | R78: 5 | S78: 5 | T78: -5 | V78: 5 | X78: 5 | Y78: 5 | Z78: 5 | AA78: 0.6 | AB78: 0.066 | AD78: =1/2 -> 0.5 | AP78: =1/2 -> 0.5 | BI78: =1/2 -> 0.5 | BU78: =1/2 -> 0.5 | CG78: =1/2 -> 0.5 | CL78: =-1/2 -> -0.5 | DK78: =1/2 -> 0.5 | EJ78: =1/2 -> 0.5 | ET78: =1/2 -> 0.5 | FF78: =1/2 -> 0.5 | FR78: =1/2 -> 0.5 | GK78: =1/2 -> 0.5 | GW78: =1/2 -> 0.5 | HI78: =1/2 -> 0.5 | HN78: =-1/2 -> -0.5 | IM78: =1/2 -> 0.5 | JL78: =1/2 -> 0.5 | JV78: =1/2 -> 0.5 | KH78: =1/2 -> 0.5 | LA78: 0.4 | LG78: 178800
A79: =crop!A79 -> Housing of cows is free-stall (deep bedding) | B79: =crop!B79 -> A.4.4 | D79: 11.57 | E79: 11.57 | F79: 11.57 | G79: 11.57 | H79: 11.57 | I79: -11.57 | K79: 11.57 | M79: 11.57 | N79: 11.57 | O79: 11.57 | P79: 11.57 | Q79: 11.57 | R79: 11.57 | S79: 11.57 | T79: -11.57 | V79: 11.57 | X79: 11.57 | Y79: 11.57 | Z79: 11.57 | AA79: 2.5 | AB79: 0.066 | AD79: =1.33/2 -> 0.665 | AP79: =1.33/2 -> 0.665 | BI79: =1.33/2 -> 0.665 | BU79: =1.33/2 -> 0.665 | CG79: =1.33/2 -> 0.665 | CL79: =-1.33/2 -> -0.665 | DJ79: =1.33/2 -> 0.665 | EI79: =1.33/2 -> 0.665 | EZ79: =1.33/2 -> 0.665 | FF79: =1.33/2 -> 0.665 | FR79: =1.33/2 -> 0.665 | GK79: =1.33/2 -> 0.665 | GW79: =1.33/2 -> 0.665 | HI79: =1.33/2 -> 0.665 | HN79: =-1.33/2 -> -0.665 | IL79: =1.33/2 -> 0.665 | JK79: =1.33/2 -> 0.665 | KB79: =1.33/2 -> 0.665 | KN79: =1.33/2 -> 0.665 | LG79: 156600
A80: =crop!A80 -> Housing of cows is free-stall slatted floor | B80: =crop!B80 -> A.4.5 | D80: 5 | E80: 5 | F80: 5 | G80: 5 | H80: 5 | I80: -5 | K80: 5 | M80: 5 | N80: 5 | O80: 5 | P80: 5 | Q80: 5 | R80: 5 | S80: 5 | T80: -5 | V80: 5 | X80: 5 | Y80: 5 | Z80: 5 | AA80: 0.6 | AB80: 0.066 | AD80: =1/2 -> 0.5 | AP80: =1/2 -> 0.5 | BI80: =1/2 -> 0.5 | BU80: =1/2 -> 0.5 | CG80: =1/2 -> 0.5 | CL80: =-1/2 -> -0.5 | DK80: =1/2 -> 0.5 | EJ80: =1/2 -> 0.5 | ET80: =1/2 -> 0.5 | FF80: =1/2 -> 0.5 | FR80: =1/2 -> 0.5 | GK80: =1/2 -> 0.5 | GW80: =1/2 -> 0.5 | HI80: =1/2 -> 0.5 | HN80: =-1/2 -> -0.5 | IM80: =1/2 -> 0.5 | JL80: =1/2 -> 0.5 | JV80: =1/2 -> 0.5 | KH80: =1/2 -> 0.5 | LA80: 0.9 | LG80: 153000
A81: =crop!A81 -> Housing of heifer, bulls and steers is slatted floor | B81: =crop!B81 -> A.5.1 | D81: 5 | E81: 5 | F81: 5 | G81: 5 | H81: 5 | I81: -5 | K81: 5 | M81: 5 | N81: 5 | O81: 5 | P81: 5 | Q81: 5 | R81: 5 | S81: 5 | T81: -5 | V81: 5 | X81: 5 | Y81: 5 | Z81: 5 | AD81: =1/2 -> 0.5 | AP81: =1/2 -> 0.5 | BI81: =1/2 -> 0.5 | BU81: =1/2 -> 0.5 | CG81: =1/2 -> 0.5 | CL81: =-1/2 -> -0.5 | DK81: =1/2 -> 0.5 | EJ81: =1/2 -> 0.5 | ET81: =1/2 -> 0.5 | FF81: =1/2 -> 0.5 | FR81: =1/2 -> 0.5 | GK81: =1/2 -> 0.5 | GW81: =1/2 -> 0.5 | HI81: =1/2 -> 0.5 | HN81: =-1/2 -> -0.5 | IM81: =1/2 -> 0.5 | JL81: =1/2 -> 0.5 | JV81: =1/2 -> 0.5 | KH81: =1/2 -> 0.5 | LB81: 0.4
A82: =crop!A82 -> Housing of heifer, bulls and steers is shallow bedding | B82: =crop!B82 -> A.5.2 | D82: 11.57 | E82: 11.57 | F82: 11.57 | G82: 11.57 | H82: 11.57 | I82: -11.57 | K82: 11.57 | M82: 11.57 | N82: 11.57 | O82: 11.57 | P82: 11.57 | Q82: 11.57 | R82: 11.57 | S82: 11.57 | T82: -11.57 | V82: 11.57 | X82: 11.57 | Y82: 11.57 | Z82: 11.57 | AD82: =1.33/2 -> 0.665 | AP82: =1.33/2 -> 0.665 | BI82: =1.33/2 -> 0.665 | BU82: =1.33/2 -> 0.665 | CG82: =1.33/2 -> 0.665 | CL82: =-1.33/2 -> -0.665 | DJ82: =1.33/2 -> 0.665 | EI82: =1.33/2 -> 0.665 | EZ82: =1.33/2 -> 0.665 | FF82: =1.33/2 -> 0.665 | FR82: =1.33/2 -> 0.665 | GK82: =1.33/2 -> 0.665 | GW82: =1.33/2 -> 0.665 | HI82: =1.33/2 -> 0.665 | HN82: =-1.33/2 -> -0.665 | IL82: =1.33/2 -> 0.665 | JK82: =1.33/2 -> 0.665 | KB82: =1.33/2 -> 0.665 | KN82: =1.33/2 -> 0.665 | LB82: 1.2
A83: =crop!A83 -> Housing of heifer, bulls and steers is deep bedding | B83: =crop!B83 -> A.5.3 | D83: 11.57 | E83: 11.57 | F83: 11.57 | G83: 11.57 | H83: 11.57 | I83: -11.57 | K83: 11.57 | M83: 11.57 | N83: 11.57 | O83: 11.57 | P83: 11.57 | Q83: 11.57 | R83: 11.57 | S83: 11.57 | T83: -11.57 | V83: 11.57 | X83: 11.57 | Y83: 11.57 | Z83: 11.57 | AD83: =1.33/2 -> 0.665 | AP83: =1.33/2 -> 0.665 | BI83: =1.33/2 -> 0.665 | BU83: =1.33/2 -> 0.665 | CG83: =1.33/2 -> 0.665 | CL83: =-1.33/2 -> -0.665 | DJ83: =1.33/2 -> 0.665 | EI83: =1.33/2 -> 0.665 | EZ83: =1.33/2 -> 0.665 | FF83: =1.33/2 -> 0.665 | FR83: =1.33/2 -> 0.665 | GK83: =1.33/2 -> 0.665 | GW83: =1.33/2 -> 0.665 | HI83: =1.33/2 -> 0.665 | HN83: =-1.33/2 -> -0.665 | IL83: =1.33/2 -> 0.665 | JK83: =1.33/2 -> 0.665 | KB83: =1.33/2 -> 0.665 | KN83: =1.33/2 -> 0.665
A84: =crop!A84 -> Cow feeding system: all year indoor, maize silage & soybean meal supplement | B84: =crop!B84 -> A.6.1 | AA84: 2.9 | FA84: 1.17 | KC84: 1.17 | KO84: =0.5+0.67 -> 1.17
A85: =crop!A85 -> Cow feeding system: all year indoor, sorghum silage & soybean meal supplement | B85: =crop!B85 -> A.6.2 | AA85: 2.9 | FA85: 1.17 | KC85: 1.17 | KO85: =0.5+0.67 -> 1.17
A86: =crop!A86 -> Cow feeding system: all year indoor, sorghum & alfalfa silage | B86: =crop!B86 -> A.6.3 | AA86: 2.9 | FA86: 1.17 | KC86: 1.17 | KO86: =0.5+0.67 -> 1.17
A87: =crop!A87 -> Cow feeding system: all year indoor, maize silage, alfalfa silage & soybean meal supplement | B87: =crop!B87 -> A.6.4 | AA87: 2.9 | FA87: 1.17 | KC87: 1.17 | KO87: =0.5+0.67 -> 1.17
A88: =crop!A88 -> Cow feeding system: 4 months grazing & soybean meal supplement | B88: =crop!B88 -> A.6.5 | AA88: =2.9*8/12 -> 1.9333333 | KY88: =8/12 -> 0.66666667 | LA88: =8/12 -> 0.66666667 | LE88: 1.2 | LI88: -0.125
A89: =crop!A89 -> Cow feeding system: 4 months grazing & rapeseed meal supplement | B89: =crop!B89 -> A.6.6 | AA89: =2.9*8/12 -> 1.9333333 | KY89: =8/12 -> 0.66666667 | LA89: =8/12 -> 0.66666667 | LE89: 1.2 | LI89: -0.125
A90: =crop!A90 -> Cow feeding system: 5 months grazing & rapeseed meal supplement | B90: =crop!B90 -> A.6.7 | AA90: =2.9*7/12 -> 1.6916667 | KY90: =7/12 -> 0.58333333 | LA90: =7/12 -> 0.58333333 | LE90: 1.2 | LI90: -0.25
A91: =crop!A91 -> Cow feeding system: 7 months grazing & rapeseed meal supplement | B91: =crop!B91 -> A.6.8 | AA91: =2.9*5.17/12 -> 1.2494167 | KY91: =5/12 -> 0.41666667 | LA91: =5/12 -> 0.41666667 | LE91: 1.2 | LI91: -0.25
A92: =crop!A92 -> Cow feeding system: 8 months grazing & faba bean supplement | B92: =crop!B92 -> A.6.9 | AA92: =2.9*4.16/12 -> 1.0053333 | KY92: =4/12 -> 0.33333333 | LA92: =4/12 -> 0.33333333 | LE92: 1.2 | LI92: -0.25
A93: =crop!A93 -> Cow feeding system: all year indoor, hay & rapeseed meal supplement | B93: =crop!B93 -> A.6.10 | AA93: 2.9 | FA93: =0.5+0.67 -> 1.17 | KC93: =0.5+0.67 -> 1.17 | KO93: =0.5+0.67 -> 1.17
A94: =crop!A94 -> Cow feeding system: 9 months grazing, without protein feed supplement | B94: =crop!B94 -> A.6.11 | AA94: =2.9*3/12 -> 0.725 | KY94: =3/12 -> 0.25 | LA94: =3/12 -> 0.25 | LE94: 1.2 | LI94: -0.25
A95: =crop!A95 -> No concentrate supply for lactating dairy cows | B95: =crop!B95 -> A.7.1
A96: =crop!A96 -> +1000 kg / cow / year with soybean meal and cereals | B96: =crop!B96 -> A.7.2
A97: =crop!A97 -> +500 kg / cow / year with soybean meal and cereals | B97: =crop!B97 -> A.7.3
A98: =crop!A98 -> +500 kg / cow / year with faba bean and cereals | B98: =crop!B98 -> A.7.4
A99: =crop!A99 -> Heifer feeding system: zero grazing / maize silage + soybean meal | Age at first calving: 24 months | B99: =crop!B99 -> A.8.1
A100: =crop!A100 -> Heifer feeding system: 4 months grazing / 8 months maize silage + hay + soybean meal | Age at first calving: 24 months | B100: =crop!B100 -> A.8.2 | KZ100: =8/12 -> 0.66666667 | LB100: =8/12 -> 0.66666667 | LF100: 1.2 | LI100: -0.125
...
